[{"0": {"select": ""}, "1": {"identifier": "Andrea Figueiredo"}, "2": {"organization_founded_on": "2014"}, "3": {"organization_operating_status": "Active"}, "4": {"organization": "MindMiners"}, "5": {"job_titles": "Controller"}, "6": {"organization_locations": "S\u00e3o Paulo, Sao Paulo, Brazil"}, "7": {"linkedin": "https://linkedin.com/in/andrea-figueiredo-finance"}, "8": {"job_departments": "Finance"}, "9": {"job_levels": "Manager"}, "10": {"private_work_emails": "\u2014"}, "11": {"private_personal_emails": "\u2014"}, "12": {"private_work_phones": "\u2014"}, "13": {"private_personal_phones": "\u2014"}, "14": {"num_private_contact_items": "\u2014"}, "15": {"num_emails": "1"}, "16": {"num_phones": "\u2014"}, "17": {"max_email_confidence": "Unknown"}, "18": {"max_phone_confidence": "\u2014"}, "19": {"organization_categories": "Analytics, Business Intelligence, Consumer Research, Digital Marketing, Market Research"}, "20": {"organization_num_employees_enum": "101-250"}, "21": {"organization_last_funding_type": "Seed"}, "22": {"organization_revenue_range": "\u2014"}, "23": {"organization_funding_total": "R$7,500,000"}, "24": {"organization_last_funding_at": "Jan 30, 2021"}, "25": {"organization_last_funding_total": "R$6,000,000"}, "26": {"organization_private_tags": "\u2014"}, "27": {"add_column": ""}, "length": 28, "prevObject": {"0": {"__ngContext__": 910676, "_fs": 372688}, "1": {"__ngContext__": 910729, "_fs": 372701}, "2": {"__ngContext__": 910749, "_fs": 372708}, "3": {"__ngContext__": 910757, "_fs": 372712}, "4": {"__ngContext__": 910765, "_fs": 372716}, "5": {"__ngContext__": 910781, "_fs": 372726}, "6": {"__ngContext__": 910796, "_fs": 372733}, "7": {"__ngContext__": 910817, "_fs": 372746}, "8": {"__ngContext__": 910833, "_fs": 372758}, "9": {"__ngContext__": 910846, "_fs": 372763}, "10": {"__ngContext__": 910859, "_fs": 372768}, "11": {"__ngContext__": 910869, "_fs": 372772}, "12": {"__ngContext__": 910879, "_fs": 372776}, "13": {"__ngContext__": 910889, "_fs": 372780}, "14": {"__ngContext__": 910899, "_fs": 372784}, "15": {"__ngContext__": 910909, "_fs": 372788}, "16": {"__ngContext__": 910919, "_fs": 372792}, "17": {"__ngContext__": 910929, "_fs": 372796}, "18": {"__ngContext__": 910939, "_fs": 372800}, "19": {"__ngContext__": 910949, "_fs": 372804}, "20": {"__ngContext__": 910976, "_fs": 372823}, "21": {"__ngContext__": 910984, "_fs": 372827}, "22": {"__ngContext__": 910992, "_fs": 372831}, "23": {"__ngContext__": 911002, "_fs": 372835}, "24": {"__ngContext__": 911010, "_fs": 372839}, "25": {"__ngContext__": 911018, "_fs": 372843}, "26": {"__ngContext__": 911026, "_fs": 372847}, "27": {"__ngContext__": 910676, "_fs": 372852}, "length": 28, "prevObject": {"0": {"__ngContext__": 910676, "__zone_symbol__clickfalse": [{"type": "eventTask", "state": "scheduled", "source": "HTMLElement.addEventListener:click", "zone": "angular", "runCount": 0}], "__zone_symbol__mouseoverfalse": [{"type": "eventTask", "state": "scheduled", "source": "HTMLElement.addEventListener:mouseover", "zone": "angular", "runCount": 0}], "__zone_symbol__mouseoutfalse": [{"type": "eventTask", "state": "scheduled", "source": "HTMLElement.addEventListener:mouseout", "zone": "angular", "runCount": 0}], "_fs": 372687}, "length": 1}}}, {"0": {"select": ""}, "1": {"identifier": "Daniela Balmant"}, "2": {"organization_founded_on": "2014"}, "3": {"organization_operating_status": "Active"}, "4": {"organization": "MindMiners"}, "5": {"job_titles": "Sales Professional"}, "6": {"organization_locations": "S\u00e3o Paulo, Sao Paulo, Brazil"}, "7": {"linkedin": "https://linkedin.com/in/danielabalmant"}, "8": {"job_departments": "\u2014"}, "9": {"job_levels": "Manager"}, "10": {"private_work_emails": "\u2014"}, "11": {"private_personal_emails": "\u2014"}, "12": {"private_work_phones": "\u2014"}, "13": {"private_personal_phones": "\u2014"}, "14": {"num_private_contact_items": "\u2014"}, "15": {"num_emails": "1"}, "16": {"num_phones": "\u2014"}, "17": {"max_email_confidence": "Unknown"}, "18": {"max_phone_confidence": "\u2014"}, "19": {"organization_categories": "Analytics, Business Intelligence, Consumer Research, Digital Marketing, Market Research"}, "20": {"organization_num_employees_enum": "101-250"}, "21": {"organization_last_funding_type": "Seed"}, "22": {"organization_revenue_range": "\u2014"}, "23": {"organization_funding_total": "R$7,500,000"}, "24": {"organization_last_funding_at": "Jan 30, 2021"}, "25": {"organization_last_funding_total": "R$6,000,000"}, "26": {"organization_private_tags": "\u2014"}, "27": {"add_column": ""}, "length": 28, "prevObject": {"0": {"__ngContext__": 910681, "_fs": 372854}, "1": {"__ngContext__": 911065, "_fs": 372867}, "2": {"__ngContext__": 911085, "_fs": 372874}, "3": {"__ngContext__": 911093, "_fs": 372878}, "4": {"__ngContext__": 911101, "_fs": 372882}, "5": {"__ngContext__": 911117, "_fs": 372892}, "6": {"__ngContext__": 911132, "_fs": 372899}, "7": {"__ngContext__": 911153, "_fs": 372912}, "8": {"__ngContext__": 911169, "_fs": 372924}, "9": {"__ngContext__": 911180, "_fs": 372929}, "10": {"__ngContext__": 911193, "_fs": 372934}, "11": {"__ngContext__": 911203, "_fs": 372938}, "12": {"__ngContext__": 911213, "_fs": 372942}, "13": {"__ngContext__": 911223, "_fs": 372946}, "14": {"__ngContext__": 911233, "_fs": 372950}, "15": {"__ngContext__": 911243, "_fs": 372954}, "16": {"__ngContext__": 911253, "_fs": 372958}, "17": {"__ngContext__": 911263, "_fs": 372962}, "18": {"__ngContext__": 911273, "_fs": 372966}, "19": {"__ngContext__": 911283, "_fs": 372970}, "20": {"__ngContext__": 911310, "_fs": 372989}, "21": {"__ngContext__": 911318, "_fs": 372993}, "22": {"__ngContext__": 911326, "_fs": 372997}, "23": {"__ngContext__": 911336, "_fs": 373001}, "24": {"__ngContext__": 911344, "_fs": 373005}, "25": {"__ngContext__": 911352, "_fs": 373009}, "26": {"__ngContext__": 911360, "_fs": 373013}, "27": {"__ngContext__": 910681, "_fs": 373018}, "length": 28, "prevObject": {"0": {"__ngContext__": 910681, "__zone_symbol__clickfalse": [{"type": "eventTask", "state": "scheduled", "source": "HTMLElement.addEventListener:click", "zone": "angular", "runCount": 0}], "__zone_symbol__mouseoverfalse": [{"type": "eventTask", "state": "scheduled", "source": "HTMLElement.addEventListener:mouseover", "zone": "angular", "runCount": 0}], "__zone_symbol__mouseoutfalse": [{"type": "eventTask", "state": "scheduled", "source": "HTMLElement.addEventListener:mouseout", "zone": "angular", "runCount": 0}], "_fs": 372853}, "length": 1}}}, {"0": {"select": ""}, "1": {"identifier": "Raphael Torquato"}, "2": {"organization_founded_on": "2014"}, "3": {"organization_operating_status": "Active"}, "4": {"organization": "MindMiners"}, "5": {"job_titles": "Manager, Manager, Engineering, Software Engineering Manager"}, "6": {"organization_locations": "S\u00e3o Paulo, Sao Paulo, Brazil"}, "7": {"linkedin": "https://linkedin.com/in/raphaeltorquato"}, "8": {"job_departments": "Engineering"}, "9": {"job_levels": "Manager"}, "10": {"private_work_emails": "\u2014"}, "11": {"private_personal_emails": "\u2014"}, "12": {"private_work_phones": "\u2014"}, "13": {"private_personal_phones": "\u2014"}, "14": {"num_private_contact_items": "\u2014"}, "15": {"num_emails": "1"}, "16": {"num_phones": "\u2014"}, "17": {"max_email_confidence": "Unknown"}, "18": {"max_phone_confidence": "\u2014"}, "19": {"organization_categories": "Analytics, Business Intelligence, Consumer Research, Digital Marketing, Market Research"}, "20": {"organization_num_employees_enum": "101-250"}, "21": {"organization_last_funding_type": "Seed"}, "22": {"organization_revenue_range": "\u2014"}, "23": {"organization_funding_total": "R$7,500,000"}, "24": {"organization_last_funding_at": "Jan 30, 2021"}, "25": {"organization_last_funding_total": "R$6,000,000"}, "26": {"organization_private_tags": "\u2014"}, "27": {"add_column": ""}, "length": 28, "prevObject": {"0": {"__ngContext__": 910686, "_fs": 373020}, "1": {"__ngContext__": 911399, "_fs": 373033}, "2": {"__ngContext__": 911419, "_fs": 373040}, "3": {"__ngContext__": 911427, "_fs": 373044}, "4": {"__ngContext__": 911435, "_fs": 373048}, "5": {"__ngContext__": 911451, "_fs": 373058}, "6": {"__ngContext__": 911472, "_fs": 373071}, "7": {"__ngContext__": 911493, "_fs": 373084}, "8": {"__ngContext__": 911509, "_fs": 373096}, "9": {"__ngContext__": 911522, "_fs": 373101}, "10": {"__ngContext__": 911535, "_fs": 373106}, "11": {"__ngContext__": 911545, "_fs": 373110}, "12": {"__ngContext__": 911555, "_fs": 373114}, "13": {"__ngContext__": 911565, "_fs": 373118}, "14": {"__ngContext__": 911575, "_fs": 373122}, "15": {"__ngContext__": 911585, "_fs": 373126}, "16": {"__ngContext__": 911595, "_fs": 373130}, "17": {"__ngContext__": 911605, "_fs": 373134}, "18": {"__ngContext__": 911615, "_fs": 373138}, "19": {"__ngContext__": 911625, "_fs": 373142}, "20": {"__ngContext__": 911652, "_fs": 373161}, "21": {"__ngContext__": 911660, "_fs": 373165}, "22": {"__ngContext__": 911668, "_fs": 373169}, "23": {"__ngContext__": 911678, "_fs": 373173}, "24": {"__ngContext__": 911686, "_fs": 373177}, "25": {"__ngContext__": 911694, "_fs": 373181}, "26": {"__ngContext__": 911702, "_fs": 373185}, "27": {"__ngContext__": 910686, "_fs": 373190}, "length": 28, "prevObject": {"0": {"__ngContext__": 910686, "__zone_symbol__clickfalse": [{"type": "eventTask", "state": "scheduled", "source": "HTMLElement.addEventListener:click", "zone": "angular", "runCount": 0}], "__zone_symbol__mouseoverfalse": [{"type": "eventTask", "state": "scheduled", "source": "HTMLElement.addEventListener:mouseover", "zone": "angular", "runCount": 0}], "__zone_symbol__mouseoutfalse": [{"type": "eventTask", "state": "scheduled", "source": "HTMLElement.addEventListener:mouseout", "zone": "angular", "runCount": 0}], "_fs": 373019}, "length": 1}}}, {"0": {"select": ""}, "1": {"identifier": "Luciana Nicolette Bilia"}, "2": {"organization_founded_on": "2014"}, "3": {"organization_operating_status": "Active"}, "4": {"organization": "MindMiners"}, "5": {"job_titles": "Sales Professional"}, "6": {"organization_locations": "S\u00e3o Paulo, Sao Paulo, Brazil"}, "7": {"linkedin": "https://linkedin.com/in/luciana-nicolette-bilia-a73879182"}, "8": {"job_departments": "Operations,\u00a0Support"}, "9": {"job_levels": "Non-Management,\u00a0Manager"}, "10": {"private_work_emails": "\u2014"}, "11": {"private_personal_emails": "\u2014"}, "12": {"private_work_phones": "\u2014"}, "13": {"private_personal_phones": "\u2014"}, "14": {"num_private_contact_items": "\u2014"}, "15": {"num_emails": "3"}, "16": {"num_phones": "\u2014"}, "17": {"max_email_confidence": "Unknown"}, "18": {"max_phone_confidence": "\u2014"}, "19": {"organization_categories": "Analytics, Business Intelligence, Consumer Research, Digital Marketing, Market Research"}, "20": {"organization_num_employees_enum": "101-250"}, "21": {"organization_last_funding_type": "Seed"}, "22": {"organization_revenue_range": "\u2014"}, "23": {"organization_funding_total": "R$7,500,000"}, "24": {"organization_last_funding_at": "Jan 30, 2021"}, "25": {"organization_last_funding_total": "R$6,000,000"}, "26": {"organization_private_tags": "\u2014"}, "27": {"add_column": ""}, "length": 28, "prevObject": {"0": {"__ngContext__": 910691, "_fs": 373192}, "1": {"__ngContext__": 911741, "_fs": 373205}, "2": {"__ngContext__": 911761, "_fs": 373212}, "3": {"__ngContext__": 911769, "_fs": 373216}, "4": {"__ngContext__": 911777, "_fs": 373220}, "5": {"__ngContext__": 911793, "_fs": 373230}, "6": {"__ngContext__": 911808, "_fs": 373237}, "7": {"__ngContext__": 911829, "_fs": 373250}, "8": {"__ngContext__": 911845, "_fs": 373262}, "9": {"__ngContext__": 911861, "_fs": 373271}, "10": {"__ngContext__": 911877, "_fs": 373280}, "11": {"__ngContext__": 911887, "_fs": 373284}, "12": {"__ngContext__": 911897, "_fs": 373288}, "13": {"__ngContext__": 911907, "_fs": 373292}, "14": {"__ngContext__": 911917, "_fs": 373296}, "15": {"__ngContext__": 911927, "_fs": 373300}, "16": {"__ngContext__": 911937, "_fs": 373304}, "17": {"__ngContext__": 911947, "_fs": 373308}, "18": {"__ngContext__": 911957, "_fs": 373312}, "19": {"__ngContext__": 911967, "_fs": 373316}, "20": {"__ngContext__": 911994, "_fs": 373335}, "21": {"__ngContext__": 912002, "_fs": 373339}, "22": {"__ngContext__": 912010, "_fs": 373343}, "23": {"__ngContext__": 912020, "_fs": 373347}, "24": {"__ngContext__": 912028, "_fs": 373351}, "25": {"__ngContext__": 912036, "_fs": 373355}, "26": {"__ngContext__": 912044, "_fs": 373359}, "27": {"__ngContext__": 910691, "_fs": 373364}, "length": 28, "prevObject": {"0": {"__ngContext__": 910691, "__zone_symbol__clickfalse": [{"type": "eventTask", "state": "scheduled", "source": "HTMLElement.addEventListener:click", "zone": "angular", "runCount": 0}], "__zone_symbol__mouseoverfalse": [{"type": "eventTask", "state": "scheduled", "source": "HTMLElement.addEventListener:mouseover", "zone": "angular", "runCount": 0}], "__zone_symbol__mouseoutfalse": [{"type": "eventTask", "state": "scheduled", "source": "HTMLElement.addEventListener:mouseout", "zone": "angular", "runCount": 0}], "_fs": 373191}, "length": 1}}}, {"0": {"select": ""}, "1": {"identifier": "Tha\u00eds Camargo"}, "2": {"organization_founded_on": "2014"}, "3": {"organization_operating_status": "Active"}, "4": {"organization": "MindMiners"}, "5": {"job_titles": "Marketing Professional"}, "6": {"organization_locations": "S\u00e3o Paulo, Sao Paulo, Brazil"}, "7": {"linkedin": "https://linkedin.com/in/thaiscamargo1"}, "8": {"job_departments": "Product"}, "9": {"job_levels": "Manager"}, "10": {"private_work_emails": "\u2014"}, "11": {"private_personal_emails": "\u2014"}, "12": {"private_work_phones": "\u2014"}, "13": {"private_personal_phones": "\u2014"}, "14": {"num_private_contact_items": "\u2014"}, "15": {"num_emails": "2"}, "16": {"num_phones": "\u2014"}, "17": {"max_email_confidence": "Unknown"}, "18": {"max_phone_confidence": "\u2014"}, "19": {"organization_categories": "Analytics, Business Intelligence, Consumer Research, Digital Marketing, Market Research"}, "20": {"organization_num_employees_enum": "101-250"}, "21": {"organization_last_funding_type": "Seed"}, "22": {"organization_revenue_range": "\u2014"}, "23": {"organization_funding_total": "R$7,500,000"}, "24": {"organization_last_funding_at": "Jan 30, 2021"}, "25": {"organization_last_funding_total": "R$6,000,000"}, "26": {"organization_private_tags": "\u2014"}, "27": {"add_column": ""}, "length": 28, "prevObject": {"0": {"__ngContext__": 910696, "_fs": 373366}, "1": {"__ngContext__": 912083, "_fs": 373379}, "2": {"__ngContext__": 912103, "_fs": 373386}, "3": {"__ngContext__": 912111, "_fs": 373390}, "4": {"__ngContext__": 912119, "_fs": 373394}, "5": {"__ngContext__": 912135, "_fs": 373404}, "6": {"__ngContext__": 912150, "_fs": 373411}, "7": {"__ngContext__": 912171, "_fs": 373424}, "8": {"__ngContext__": 912187, "_fs": 373436}, "9": {"__ngContext__": 912200, "_fs": 373441}, "10": {"__ngContext__": 912213, "_fs": 373446}, "11": {"__ngContext__": 912223, "_fs": 373450}, "12": {"__ngContext__": 912233, "_fs": 373454}, "13": {"__ngContext__": 912243, "_fs": 373458}, "14": {"__ngContext__": 912253, "_fs": 373462}, "15": {"__ngContext__": 912263, "_fs": 373466}, "16": {"__ngContext__": 912273, "_fs": 373470}, "17": {"__ngContext__": 912283, "_fs": 373474}, "18": {"__ngContext__": 912293, "_fs": 373478}, "19": {"__ngContext__": 912303, "_fs": 373482}, "20": {"__ngContext__": 912330, "_fs": 373501}, "21": {"__ngContext__": 912338, "_fs": 373505}, "22": {"__ngContext__": 912346, "_fs": 373509}, "23": {"__ngContext__": 912356, "_fs": 373513}, "24": {"__ngContext__": 912364, "_fs": 373517}, "25": {"__ngContext__": 912372, "_fs": 373521}, "26": {"__ngContext__": 912380, "_fs": 373525}, "27": {"__ngContext__": 910696, "_fs": 373530}, "length": 28, "prevObject": {"0": {"__ngContext__": 910696, "__zone_symbol__clickfalse": [{"type": "eventTask", "state": "scheduled", "source": "HTMLElement.addEventListener:click", "zone": "angular", "runCount": 0}], "__zone_symbol__mouseoverfalse": [{"type": "eventTask", "state": "scheduled", "source": "HTMLElement.addEventListener:mouseover", "zone": "angular", "runCount": 0}], "__zone_symbol__mouseoutfalse": [{"type": "eventTask", "state": "scheduled", "source": "HTMLElement.addEventListener:mouseout", "zone": "angular", "runCount": 0}], "_fs": 373365}, "length": 1}}}, {"0": {"select": ""}, "1": {"identifier": "Gustavo Barreto"}, "2": {"organization_founded_on": "Aug 1, 2019"}, "3": {"organization_operating_status": "Active"}, "4": {"organization": "Fintalk AI"}, "5": {"job_titles": "\u2014"}, "6": {"organization_locations": "S\u00e3o Paulo, Sao Paulo, Brazil"}, "7": {"linkedin": "https://linkedin.com/in/gustawobarreto"}, "8": {"job_departments": "\u2014"}, "9": {"job_levels": "\u2014"}, "10": {"private_work_emails": "\u2014"}, "11": {"private_personal_emails": "\u2014"}, "12": {"private_work_phones": "\u2014"}, "13": {"private_personal_phones": "\u2014"}, "14": {"num_private_contact_items": "\u2014"}, "15": {"num_emails": "1"}, "16": {"num_phones": "\u2014"}, "17": {"max_email_confidence": "Unknown"}, "18": {"max_phone_confidence": "\u2014"}, "19": {"organization_categories": "Artificial Intelligence (AI), Customer Service, Debt Collections, E-Commerce, Field Support, Sales Automation, Software"}, "20": {"organization_num_employees_enum": "11-50"}, "21": {"organization_last_funding_type": "Seed"}, "22": {"organization_revenue_range": "$1M to $10M"}, "23": {"organization_funding_total": "$2,000,981"}, "24": {"organization_last_funding_at": "Jan 19, 2024"}, "25": {"organization_last_funding_total": "\u2014"}, "26": {"organization_private_tags": "\u2014"}, "27": {"add_column": ""}, "length": 28, "prevObject": {"0": {"__ngContext__": 912393, "_fs": 373532}, "1": {"__ngContext__": 912444, "_fs": 373545}, "2": {"__ngContext__": 912464, "_fs": 373552}, "3": {"__ngContext__": 912472, "_fs": 373556}, "4": {"__ngContext__": 912480, "_fs": 373560}, "5": {"__ngContext__": 912496, "_fs": 373570}, "6": {"__ngContext__": 912509, "_fs": 373575}, "7": {"__ngContext__": 912530, "_fs": 373588}, "8": {"__ngContext__": 912546, "_fs": 373600}, "9": {"__ngContext__": 912557, "_fs": 373605}, "10": {"__ngContext__": 912568, "_fs": 373610}, "11": {"__ngContext__": 912578, "_fs": 373614}, "12": {"__ngContext__": 912588, "_fs": 373618}, "13": {"__ngContext__": 912598, "_fs": 373622}, "14": {"__ngContext__": 912608, "_fs": 373626}, "15": {"__ngContext__": 912618, "_fs": 373630}, "16": {"__ngContext__": 912628, "_fs": 373634}, "17": {"__ngContext__": 912638, "_fs": 373638}, "18": {"__ngContext__": 912648, "_fs": 373642}, "19": {"__ngContext__": 912658, "_fs": 373646}, "20": {"__ngContext__": 912691, "_fs": 373671}, "21": {"__ngContext__": 912699, "_fs": 373675}, "22": {"__ngContext__": 912707, "_fs": 373679}, "23": {"__ngContext__": 912715, "_fs": 373683}, "24": {"__ngContext__": 912723, "_fs": 373687}, "25": {"__ngContext__": 912731, "_fs": 373691}, "26": {"__ngContext__": 912741, "_fs": 373695}, "27": {"__ngContext__": 912393, "_fs": 373700}, "length": 28, "prevObject": {"0": {"__ngContext__": 912393, "__zone_symbol__clickfalse": [{"type": "eventTask", "state": "scheduled", "source": "HTMLElement.addEventListener:click", "zone": "angular", "runCount": 0}], "__zone_symbol__mouseoverfalse": [{"type": "eventTask", "state": "scheduled", "source": "HTMLElement.addEventListener:mouseover", "zone": "angular", "runCount": 0}], "__zone_symbol__mouseoutfalse": [{"type": "eventTask", "state": "scheduled", "source": "HTMLElement.addEventListener:mouseout", "zone": "angular", "runCount": 0}], "_fs": 373531}, "length": 1}}}, {"0": {"select": ""}, "1": {"identifier": "Gabriel Carvalho"}, "2": {"organization_founded_on": "2022"}, "3": {"organization_operating_status": "Active"}, "4": {"organization": "Teachy"}, "5": {"job_titles": "Engineer"}, "6": {"organization_locations": "Botafogo, Rio de Janeiro, Brazil"}, "7": {"linkedin": "https://linkedin.com/in/gabriel-carvalho-b11129180"}, "8": {"job_departments": "Engineering"}, "9": {"job_levels": "Non-Management"}, "10": {"private_work_emails": "\u2014"}, "11": {"private_personal_emails": "\u2014"}, "12": {"private_work_phones": "\u2014"}, "13": {"private_personal_phones": "\u2014"}, "14": {"num_private_contact_items": "\u2014"}, "15": {"num_emails": "1"}, "16": {"num_phones": "\u2014"}, "17": {"max_email_confidence": "Unknown"}, "18": {"max_phone_confidence": "\u2014"}, "19": {"organization_categories": "Artificial Intelligence (AI), EdTech, Education"}, "20": {"organization_num_employees_enum": "11-50"}, "21": {"organization_last_funding_type": "Pre-Seed"}, "22": {"organization_revenue_range": "\u2014"}, "23": {"organization_funding_total": "$1,600,000"}, "24": {"organization_last_funding_at": "Jul 12, 2023"}, "25": {"organization_last_funding_total": "$1,600,000"}, "26": {"organization_private_tags": "\u2014"}, "27": {"add_column": ""}, "length": 28, "prevObject": {"0": {"__ngContext__": 912398, "_fs": 373702}, "1": {"__ngContext__": 912780, "_fs": 373715}, "2": {"__ngContext__": 912800, "_fs": 373722}, "3": {"__ngContext__": 912808, "_fs": 373726}, "4": {"__ngContext__": 912816, "_fs": 373730}, "5": {"__ngContext__": 912832, "_fs": 373740}, "6": {"__ngContext__": 912847, "_fs": 373747}, "7": {"__ngContext__": 912868, "_fs": 373760}, "8": {"__ngContext__": 912884, "_fs": 373772}, "9": {"__ngContext__": 912897, "_fs": 373777}, "10": {"__ngContext__": 912910, "_fs": 373782}, "11": {"__ngContext__": 912920, "_fs": 373786}, "12": {"__ngContext__": 912930, "_fs": 373790}, "13": {"__ngContext__": 912940, "_fs": 373794}, "14": {"__ngContext__": 912950, "_fs": 373798}, "15": {"__ngContext__": 912960, "_fs": 373802}, "16": {"__ngContext__": 912970, "_fs": 373806}, "17": {"__ngContext__": 912980, "_fs": 373810}, "18": {"__ngContext__": 912990, "_fs": 373814}, "19": {"__ngContext__": 913000, "_fs": 373818}, "20": {"__ngContext__": 913021, "_fs": 373831}, "21": {"__ngContext__": 913029, "_fs": 373835}, "22": {"__ngContext__": 913037, "_fs": 373839}, "23": {"__ngContext__": 913047, "_fs": 373843}, "24": {"__ngContext__": 913055, "_fs": 373847}, "25": {"__ngContext__": 913063, "_fs": 373851}, "26": {"__ngContext__": 913071, "_fs": 373855}, "27": {"__ngContext__": 912398, "_fs": 373860}, "length": 28, "prevObject": {"0": {"__ngContext__": 912398, "__zone_symbol__clickfalse": [{"type": "eventTask", "state": "scheduled", "source": "HTMLElement.addEventListener:click", "zone": "angular", "runCount": 0}], "__zone_symbol__mouseoverfalse": [{"type": "eventTask", "state": "scheduled", "source": "HTMLElement.addEventListener:mouseover", "zone": "angular", "runCount": 0}], "__zone_symbol__mouseoutfalse": [{"type": "eventTask", "state": "scheduled", "source": "HTMLElement.addEventListener:mouseout", "zone": "angular", "runCount": 0}], "_fs": 373701}, "length": 1}}}, {"0": {"select": ""}, "1": {"identifier": "Mar\u00eda Freixas"}, "2": {"organization_founded_on": "2011"}, "3": {"organization_operating_status": "Active"}, "4": {"organization": "Logan"}, "5": {"job_titles": "\u2014"}, "6": {"organization_locations": "Buenos Aires, Distrito Federal, Argentina"}, "7": {"linkedin": "https://linkedin.com/in/luisafreixas"}, "8": {"job_departments": "\u2014"}, "9": {"job_levels": "Manager"}, "10": {"private_work_emails": "\u2014"}, "11": {"private_personal_emails": "\u2014"}, "12": {"private_work_phones": "\u2014"}, "13": {"private_personal_phones": "\u2014"}, "14": {"num_private_contact_items": "\u2014"}, "15": {"num_emails": "1"}, "16": {"num_phones": "\u2014"}, "17": {"max_email_confidence": "Unknown"}, "18": {"max_phone_confidence": "\u2014"}, "19": {"organization_categories": "Advertising, Mobile, Publishing"}, "20": {"organization_num_employees_enum": "51-100"}, "21": {"organization_last_funding_type": "Series A"}, "22": {"organization_revenue_range": "$10M to $50M"}, "23": {"organization_funding_total": "$2,025,000"}, "24": {"organization_last_funding_at": "Oct 6, 2016"}, "25": {"organization_last_funding_total": "$2,000,000"}, "26": {"organization_private_tags": "\u2014"}, "27": {"add_column": ""}, "length": 28, "prevObject": {"0": {"__ngContext__": 912403, "_fs": 373862}, "1": {"__ngContext__": 913110, "_fs": 373875}, "2": {"__ngContext__": 913130, "_fs": 373882}, "3": {"__ngContext__": 913138, "_fs": 373886}, "4": {"__ngContext__": 913146, "_fs": 373890}, "5": {"__ngContext__": 913162, "_fs": 373900}, "6": {"__ngContext__": 913175, "_fs": 373905}, "7": {"__ngContext__": 913196, "_fs": 373918}, "8": {"__ngContext__": 913212, "_fs": 373930}, "9": {"__ngContext__": 913223, "_fs": 373935}, "10": {"__ngContext__": 913236, "_fs": 373940}, "11": {"__ngContext__": 913246, "_fs": 373944}, "12": {"__ngContext__": 913256, "_fs": 373948}, "13": {"__ngContext__": 913266, "_fs": 373952}, "14": {"__ngContext__": 913276, "_fs": 373956}, "15": {"__ngContext__": 913286, "_fs": 373960}, "16": {"__ngContext__": 913296, "_fs": 373964}, "17": {"__ngContext__": 913306, "_fs": 373968}, "18": {"__ngContext__": 913316, "_fs": 373972}, "19": {"__ngContext__": 913326, "_fs": 373976}, "20": {"__ngContext__": 913347, "_fs": 373989}, "21": {"__ngContext__": 913355, "_fs": 373993}, "22": {"__ngContext__": 913363, "_fs": 373997}, "23": {"__ngContext__": 913371, "_fs": 374001}, "24": {"__ngContext__": 913379, "_fs": 374005}, "25": {"__ngContext__": 913387, "_fs": 374009}, "26": {"__ngContext__": 913395, "_fs": 374013}, "27": {"__ngContext__": 912403, "_fs": 374018}, "length": 28, "prevObject": {"0": {"__ngContext__": 912403, "__zone_symbol__clickfalse": [{"type": "eventTask", "state": "scheduled", "source": "HTMLElement.addEventListener:click", "zone": "angular", "runCount": 0}], "__zone_symbol__mouseoverfalse": [{"type": "eventTask", "state": "scheduled", "source": "HTMLElement.addEventListener:mouseover", "zone": "angular", "runCount": 0}], "__zone_symbol__mouseoutfalse": [{"type": "eventTask", "state": "scheduled", "source": "HTMLElement.addEventListener:mouseout", "zone": "angular", "runCount": 0}], "_fs": 373861}, "length": 1}}}, {"0": {"select": ""}, "1": {"identifier": "Mike Penny"}, "2": {"organization_founded_on": "2011"}, "3": {"organization_operating_status": "Active"}, "4": {"organization": "Logan"}, "5": {"job_titles": "\u2014"}, "6": {"organization_locations": "Buenos Aires, Distrito Federal, Argentina"}, "7": {"linkedin": "https://linkedin.com/in/nextheory"}, "8": {"job_departments": "\u2014"}, "9": {"job_levels": "Manager"}, "10": {"private_work_emails": "\u2014"}, "11": {"private_personal_emails": "\u2014"}, "12": {"private_work_phones": "\u2014"}, "13": {"private_personal_phones": "\u2014"}, "14": {"num_private_contact_items": "\u2014"}, "15": {"num_emails": "1"}, "16": {"num_phones": "\u2014"}, "17": {"max_email_confidence": "Unknown"}, "18": {"max_phone_confidence": "\u2014"}, "19": {"organization_categories": "Advertising, Mobile, Publishing"}, "20": {"organization_num_employees_enum": "51-100"}, "21": {"organization_last_funding_type": "Series A"}, "22": {"organization_revenue_range": "$10M to $50M"}, "23": {"organization_funding_total": "$2,025,000"}, "24": {"organization_last_funding_at": "Oct 6, 2016"}, "25": {"organization_last_funding_total": "$2,000,000"}, "26": {"organization_private_tags": "\u2014"}, "27": {"add_column": ""}, "length": 28, "prevObject": {"0": {"__ngContext__": 912408, "_fs": 374020}, "1": {"__ngContext__": 913434, "_fs": 374033}, "2": {"__ngContext__": 913454, "_fs": 374040}, "3": {"__ngContext__": 913462, "_fs": 374044}, "4": {"__ngContext__": 913470, "_fs": 374048}, "5": {"__ngContext__": 913486, "_fs": 374058}, "6": {"__ngContext__": 913499, "_fs": 374063}, "7": {"__ngContext__": 913520, "_fs": 374076}, "8": {"__ngContext__": 913536, "_fs": 374088}, "9": {"__ngContext__": 913547, "_fs": 374093}, "10": {"__ngContext__": 913560, "_fs": 374098}, "11": {"__ngContext__": 913570, "_fs": 374102}, "12": {"__ngContext__": 913580, "_fs": 374106}, "13": {"__ngContext__": 913590, "_fs": 374110}, "14": {"__ngContext__": 913600, "_fs": 374114}, "15": {"__ngContext__": 913610, "_fs": 374118}, "16": {"__ngContext__": 913620, "_fs": 374122}, "17": {"__ngContext__": 913630, "_fs": 374126}, "18": {"__ngContext__": 913640, "_fs": 374130}, "19": {"__ngContext__": 913650, "_fs": 374134}, "20": {"__ngContext__": 913671, "_fs": 374147}, "21": {"__ngContext__": 913679, "_fs": 374151}, "22": {"__ngContext__": 913687, "_fs": 374155}, "23": {"__ngContext__": 913695, "_fs": 374159}, "24": {"__ngContext__": 913703, "_fs": 374163}, "25": {"__ngContext__": 913711, "_fs": 374167}, "26": {"__ngContext__": 913719, "_fs": 374171}, "27": {"__ngContext__": 912408, "_fs": 374176}, "length": 28, "prevObject": {"0": {"__ngContext__": 912408, "__zone_symbol__clickfalse": [{"type": "eventTask", "state": "scheduled", "source": "HTMLElement.addEventListener:click", "zone": "angular", "runCount": 0}], "__zone_symbol__mouseoverfalse": [{"type": "eventTask", "state": "scheduled", "source": "HTMLElement.addEventListener:mouseover", "zone": "angular", "runCount": 0}], "__zone_symbol__mouseoutfalse": [{"type": "eventTask", "state": "scheduled", "source": "HTMLElement.addEventListener:mouseout", "zone": "angular", "runCount": 0}], "_fs": 374019}, "length": 1}}}, {"0": {"select": ""}, "1": {"identifier": "Renan Antunes da Gama"}, "2": {"organization_founded_on": "Nov 11, 2016"}, "3": {"organization_operating_status": "Active"}, "4": {"organization": "Insider Store"}, "5": {"job_titles": "Engineer"}, "6": {"organization_locations": "S\u00e3o Paulo, Sao Paulo, Brazil"}, "7": {"linkedin": "https://linkedin.com/in/renan-antunes-da-gama"}, "8": {"job_departments": "Engineering"}, "9": {"job_levels": "Non-Management"}, "10": {"private_work_emails": "\u2014"}, "11": {"private_personal_emails": "\u2014"}, "12": {"private_work_phones": "\u2014"}, "13": {"private_personal_phones": "\u2014"}, "14": {"num_private_contact_items": "\u2014"}, "15": {"num_emails": "2"}, "16": {"num_phones": "\u2014"}, "17": {"max_email_confidence": "Unknown"}, "18": {"max_phone_confidence": "\u2014"}, "19": {"organization_categories": "E-Commerce, Fashion, Retail"}, "20": {"organization_num_employees_enum": "51-100"}, "21": {"organization_last_funding_type": "Debt Financing"}, "22": {"organization_revenue_range": "\u2014"}, "23": {"organization_funding_total": "R$12,000,000"}, "24": {"organization_last_funding_at": "Aug 9, 2021"}, "25": {"organization_last_funding_total": "R$12,000,000"}, "26": {"organization_private_tags": "\u2014"}, "27": {"add_column": ""}, "length": 28, "prevObject": {"0": {"__ngContext__": 912413, "_fs": 374178}, "1": {"__ngContext__": 913758, "_fs": 374191}, "2": {"__ngContext__": 913778, "_fs": 374198}, "3": {"__ngContext__": 913786, "_fs": 374202}, "4": {"__ngContext__": 913794, "_fs": 374206}, "5": {"__ngContext__": 913810, "_fs": 374216}, "6": {"__ngContext__": 913825, "_fs": 374223}, "7": {"__ngContext__": 913846, "_fs": 374236}, "8": {"__ngContext__": 913862, "_fs": 374248}, "9": {"__ngContext__": 913875, "_fs": 374253}, "10": {"__ngContext__": 913888, "_fs": 374258}, "11": {"__ngContext__": 913898, "_fs": 374262}, "12": {"__ngContext__": 913908, "_fs": 374266}, "13": {"__ngContext__": 913918, "_fs": 374270}, "14": {"__ngContext__": 913928, "_fs": 374274}, "15": {"__ngContext__": 913938, "_fs": 374278}, "16": {"__ngContext__": 913948, "_fs": 374282}, "17": {"__ngContext__": 913958, "_fs": 374286}, "18": {"__ngContext__": 913968, "_fs": 374290}, "19": {"__ngContext__": 913978, "_fs": 374294}, "20": {"__ngContext__": 913999, "_fs": 374307}, "21": {"__ngContext__": 914007, "_fs": 374311}, "22": {"__ngContext__": 914015, "_fs": 374315}, "23": {"__ngContext__": 914025, "_fs": 374319}, "24": {"__ngContext__": 914033, "_fs": 374323}, "25": {"__ngContext__": 914041, "_fs": 374327}, "26": {"__ngContext__": 914049, "_fs": 374331}, "27": {"__ngContext__": 912413, "_fs": 374336}, "length": 28, "prevObject": {"0": {"__ngContext__": 912413, "__zone_symbol__clickfalse": [{"type": "eventTask", "state": "scheduled", "source": "HTMLElement.addEventListener:click", "zone": "angular", "runCount": 0}], "__zone_symbol__mouseoverfalse": [{"type": "eventTask", "state": "scheduled", "source": "HTMLElement.addEventListener:mouseover", "zone": "angular", "runCount": 0}], "__zone_symbol__mouseoutfalse": [{"type": "eventTask", "state": "scheduled", "source": "HTMLElement.addEventListener:mouseout", "zone": "angular", "runCount": 0}], "_fs": 374177}, "length": 1}}}, {"0": {"select": ""}, "1": {"identifier": "Felipe Antunes"}, "2": {"organization_founded_on": "Nov 11, 2016"}, "3": {"organization_operating_status": "Active"}, "4": {"organization": "Insider Store"}, "5": {"job_titles": "\u2014"}, "6": {"organization_locations": "S\u00e3o Paulo, Sao Paulo, Brazil"}, "7": {"linkedin": "https://linkedin.com/in/feantunes"}, "8": {"job_departments": "Information Technology"}, "9": {"job_levels": "Non-Management"}, "10": {"private_work_emails": "\u2014"}, "11": {"private_personal_emails": "\u2014"}, "12": {"private_work_phones": "\u2014"}, "13": {"private_personal_phones": "\u2014"}, "14": {"num_private_contact_items": "\u2014"}, "15": {"num_emails": "1"}, "16": {"num_phones": "\u2014"}, "17": {"max_email_confidence": "Unknown"}, "18": {"max_phone_confidence": "\u2014"}, "19": {"organization_categories": "E-Commerce, Fashion, Retail"}, "20": {"organization_num_employees_enum": "51-100"}, "21": {"organization_last_funding_type": "Debt Financing"}, "22": {"organization_revenue_range": "\u2014"}, "23": {"organization_funding_total": "R$12,000,000"}, "24": {"organization_last_funding_at": "Aug 9, 2021"}, "25": {"organization_last_funding_total": "R$12,000,000"}, "26": {"organization_private_tags": "\u2014"}, "27": {"add_column": ""}, "length": 28, "prevObject": {"0": {"__ngContext__": 914062}, "1": {"__ngContext__": 914113}, "2": {"__ngContext__": 914133}, "3": {"__ngContext__": 914141}, "4": {"__ngContext__": 914149}, "5": {"__ngContext__": 914165}, "6": {"__ngContext__": 914178}, "7": {"__ngContext__": 914199}, "8": {"__ngContext__": 914215}, "9": {"__ngContext__": 914228}, "10": {"__ngContext__": 914241}, "11": {"__ngContext__": 914251}, "12": {"__ngContext__": 914261}, "13": {"__ngContext__": 914271}, "14": {"__ngContext__": 914281}, "15": {"__ngContext__": 914291}, "16": {"__ngContext__": 914301}, "17": {"__ngContext__": 914311}, "18": {"__ngContext__": 914321}, "19": {"__ngContext__": 914331}, "20": {"__ngContext__": 914352}, "21": {"__ngContext__": 914360}, "22": {"__ngContext__": 914368}, "23": {"__ngContext__": 914378}, "24": {"__ngContext__": 914386}, "25": {"__ngContext__": 914394}, "26": {"__ngContext__": 914402}, "27": {"__ngContext__": 914062}, "length": 28, "prevObject": {"0": {"__ngContext__": 914062, "__zone_symbol__clickfalse": [{"type": "eventTask", "state": "scheduled", "source": "HTMLElement.addEventListener:click", "zone": "angular", "runCount": 0}], "__zone_symbol__mouseoverfalse": [{"type": "eventTask", "state": "scheduled", "source": "HTMLElement.addEventListener:mouseover", "zone": "angular", "runCount": 0}], "__zone_symbol__mouseoutfalse": [{"type": "eventTask", "state": "scheduled", "source": "HTMLElement.addEventListener:mouseout", "zone": "angular", "runCount": 0}]}, "length": 1}}}, {"0": {"select": ""}, "1": {"identifier": "Ingrid Gaspardi"}, "2": {"organization_founded_on": "Nov 11, 2016"}, "3": {"organization_operating_status": "Active"}, "4": {"organization": "Insider Store"}, "5": {"job_titles": "Admin, Admin, Finance"}, "6": {"organization_locations": "S\u00e3o Paulo, Sao Paulo, Brazil"}, "7": {"linkedin": "https://linkedin.com/in/ingrid-gaspardi"}, "8": {"job_departments": "Operations"}, "9": {"job_levels": "Non-Management"}, "10": {"private_work_emails": "\u2014"}, "11": {"private_personal_emails": "\u2014"}, "12": {"private_work_phones": "\u2014"}, "13": {"private_personal_phones": "\u2014"}, "14": {"num_private_contact_items": "\u2014"}, "15": {"num_emails": "2"}, "16": {"num_phones": "\u2014"}, "17": {"max_email_confidence": "Unknown"}, "18": {"max_phone_confidence": "\u2014"}, "19": {"organization_categories": "E-Commerce, Fashion, Retail"}, "20": {"organization_num_employees_enum": "51-100"}, "21": {"organization_last_funding_type": "Debt Financing"}, "22": {"organization_revenue_range": "\u2014"}, "23": {"organization_funding_total": "R$12,000,000"}, "24": {"organization_last_funding_at": "Aug 9, 2021"}, "25": {"organization_last_funding_total": "R$12,000,000"}, "26": {"organization_private_tags": "\u2014"}, "27": {"add_column": ""}, "length": 28, "prevObject": {"0": {"__ngContext__": 914067}, "1": {"__ngContext__": 914441}, "2": {"__ngContext__": 914461}, "3": {"__ngContext__": 914469}, "4": {"__ngContext__": 914477}, "5": {"__ngContext__": 914493}, "6": {"__ngContext__": 914511}, "7": {"__ngContext__": 914532}, "8": {"__ngContext__": 914548}, "9": {"__ngContext__": 914561}, "10": {"__ngContext__": 914574}, "11": {"__ngContext__": 914584}, "12": {"__ngContext__": 914594}, "13": {"__ngContext__": 914604}, "14": {"__ngContext__": 914614}, "15": {"__ngContext__": 914624}, "16": {"__ngContext__": 914634}, "17": {"__ngContext__": 914644}, "18": {"__ngContext__": 914654}, "19": {"__ngContext__": 914664}, "20": {"__ngContext__": 914685}, "21": {"__ngContext__": 914693}, "22": {"__ngContext__": 914701}, "23": {"__ngContext__": 914711}, "24": {"__ngContext__": 914719}, "25": {"__ngContext__": 914727}, "26": {"__ngContext__": 914735}, "27": {"__ngContext__": 914067}, "length": 28, "prevObject": {"0": {"__ngContext__": 914067, "__zone_symbol__clickfalse": [{"type": "eventTask", "state": "scheduled", "source": "HTMLElement.addEventListener:click", "zone": "angular", "runCount": 0}], "__zone_symbol__mouseoverfalse": [{"type": "eventTask", "state": "scheduled", "source": "HTMLElement.addEventListener:mouseover", "zone": "angular", "runCount": 0}], "__zone_symbol__mouseoutfalse": [{"type": "eventTask", "state": "scheduled", "source": "HTMLElement.addEventListener:mouseout", "zone": "angular", "runCount": 0}]}, "length": 1}}}, {"0": {"select": ""}, "1": {"identifier": "Victor Lapetina"}, "2": {"organization_founded_on": "2019"}, "3": {"organization_operating_status": "Active"}, "4": {"organization": "Linker"}, "5": {"job_titles": "Senior Software Engineer"}, "6": {"organization_locations": "S\u00e3o Paulo, Sao Paulo, Brazil"}, "7": {"linkedin": "https://linkedin.com/in/victorlapetina"}, "8": {"job_departments": "Engineering"}, "9": {"job_levels": "Non-Management"}, "10": {"private_work_emails": "\u2014"}, "11": {"private_personal_emails": "\u2014"}, "12": {"private_work_phones": "\u2014"}, "13": {"private_personal_phones": "\u2014"}, "14": {"num_private_contact_items": "\u2014"}, "15": {"num_emails": "1"}, "16": {"num_phones": "\u2014"}, "17": {"max_email_confidence": "Unknown"}, "18": {"max_phone_confidence": "\u2014"}, "19": {"organization_categories": "B2B, Banking, Finance, Financial Services"}, "20": {"organization_num_employees_enum": "51-100"}, "21": {"organization_last_funding_type": "Venture - Series Unknown"}, "22": {"organization_revenue_range": "\u2014"}, "23": {"organization_funding_total": "R$12,000,000"}, "24": {"organization_last_funding_at": "Dec 21, 2020"}, "25": {"organization_last_funding_total": "R$12,000,000"}, "26": {"organization_private_tags": "\u2014"}, "27": {"add_column": ""}, "length": 28, "prevObject": {"0": {"__ngContext__": 914072}, "1": {"__ngContext__": 914774}, "2": {"__ngContext__": 914794}, "3": {"__ngContext__": 914802}, "4": {"__ngContext__": 914810}, "5": {"__ngContext__": 914826}, "6": {"__ngContext__": 914841}, "7": {"__ngContext__": 914862}, "8": {"__ngContext__": 914878}, "9": {"__ngContext__": 914891}, "10": {"__ngContext__": 914904}, "11": {"__ngContext__": 914914}, "12": {"__ngContext__": 914924}, "13": {"__ngContext__": 914934}, "14": {"__ngContext__": 914944}, "15": {"__ngContext__": 914954}, "16": {"__ngContext__": 914964}, "17": {"__ngContext__": 914974}, "18": {"__ngContext__": 914984}, "19": {"__ngContext__": 914994}, "20": {"__ngContext__": 915018}, "21": {"__ngContext__": 915026}, "22": {"__ngContext__": 915034}, "23": {"__ngContext__": 915044}, "24": {"__ngContext__": 915052}, "25": {"__ngContext__": 915060}, "26": {"__ngContext__": 915068}, "27": {"__ngContext__": 914072}, "length": 28, "prevObject": {"0": {"__ngContext__": 914072, "__zone_symbol__clickfalse": [{"type": "eventTask", "state": "scheduled", "source": "HTMLElement.addEventListener:click", "zone": "angular", "runCount": 0}], "__zone_symbol__mouseoverfalse": [{"type": "eventTask", "state": "scheduled", "source": "HTMLElement.addEventListener:mouseover", "zone": "angular", "runCount": 0}], "__zone_symbol__mouseoutfalse": [{"type": "eventTask", "state": "scheduled", "source": "HTMLElement.addEventListener:mouseout", "zone": "angular", "runCount": 0}]}, "length": 1}}}, {"0": {"select": ""}, "1": {"identifier": "Weuller Azevedo"}, "2": {"organization_founded_on": "2019"}, "3": {"organization_operating_status": "Active"}, "4": {"organization": "Linker"}, "5": {"job_titles": "Engineer"}, "6": {"organization_locations": "S\u00e3o Paulo, Sao Paulo, Brazil"}, "7": {"linkedin": "https://linkedin.com/in/weuller-azevedo"}, "8": {"job_departments": "Engineering"}, "9": {"job_levels": "Non-Management"}, "10": {"private_work_emails": "\u2014"}, "11": {"private_personal_emails": "\u2014"}, "12": {"private_work_phones": "\u2014"}, "13": {"private_personal_phones": "\u2014"}, "14": {"num_private_contact_items": "\u2014"}, "15": {"num_emails": "1"}, "16": {"num_phones": "\u2014"}, "17": {"max_email_confidence": "Unknown"}, "18": {"max_phone_confidence": "\u2014"}, "19": {"organization_categories": "B2B, Banking, Finance, Financial Services"}, "20": {"organization_num_employees_enum": "51-100"}, "21": {"organization_last_funding_type": "Venture - Series Unknown"}, "22": {"organization_revenue_range": "\u2014"}, "23": {"organization_funding_total": "R$12,000,000"}, "24": {"organization_last_funding_at": "Dec 21, 2020"}, "25": {"organization_last_funding_total": "R$12,000,000"}, "26": {"organization_private_tags": "\u2014"}, "27": {"add_column": ""}, "length": 28, "prevObject": {"0": {"__ngContext__": 914077}, "1": {"__ngContext__": 915107}, "2": {"__ngContext__": 915127}, "3": {"__ngContext__": 915135}, "4": {"__ngContext__": 915143}, "5": {"__ngContext__": 915159}, "6": {"__ngContext__": 915174}, "7": {"__ngContext__": 915195}, "8": {"__ngContext__": 915211}, "9": {"__ngContext__": 915224}, "10": {"__ngContext__": 915237}, "11": {"__ngContext__": 915247}, "12": {"__ngContext__": 915257}, "13": {"__ngContext__": 915267}, "14": {"__ngContext__": 915277}, "15": {"__ngContext__": 915287}, "16": {"__ngContext__": 915297}, "17": {"__ngContext__": 915307}, "18": {"__ngContext__": 915317}, "19": {"__ngContext__": 915327}, "20": {"__ngContext__": 915351}, "21": {"__ngContext__": 915359}, "22": {"__ngContext__": 915367}, "23": {"__ngContext__": 915377}, "24": {"__ngContext__": 915385}, "25": {"__ngContext__": 915393}, "26": {"__ngContext__": 915401}, "27": {"__ngContext__": 914077}, "length": 28, "prevObject": {"0": {"__ngContext__": 914077, "__zone_symbol__clickfalse": [{"type": "eventTask", "state": "scheduled", "source": "HTMLElement.addEventListener:click", "zone": "angular", "runCount": 0}], "__zone_symbol__mouseoverfalse": [{"type": "eventTask", "state": "scheduled", "source": "HTMLElement.addEventListener:mouseover", "zone": "angular", "runCount": 0}], "__zone_symbol__mouseoutfalse": [{"type": "eventTask", "state": "scheduled", "source": "HTMLElement.addEventListener:mouseout", "zone": "angular", "runCount": 0}]}, "length": 1}}}, {"0": {"select": ""}, "1": {"identifier": "Eduardo Siqueira"}, "2": {"organization_founded_on": "2019"}, "3": {"organization_operating_status": "Active"}, "4": {"organization": "Munai"}, "5": {"job_titles": "Developer, Full Stack Developer"}, "6": {"organization_locations": "Curitiba, Parana, Brazil"}, "7": {"linkedin": "https://linkedin.com/in/esiqueiradev"}, "8": {"job_departments": "\u2014"}, "9": {"job_levels": "Non-Management"}, "10": {"private_work_emails": "\u2014"}, "11": {"private_personal_emails": "\u2014"}, "12": {"private_work_phones": "\u2014"}, "13": {"private_personal_phones": "\u2014"}, "14": {"num_private_contact_items": "\u2014"}, "15": {"num_emails": "1"}, "16": {"num_phones": "\u2014"}, "17": {"max_email_confidence": "Unknown"}, "18": {"max_phone_confidence": "\u2014"}, "19": {"organization_categories": "Artificial Intelligence (AI), Health Care, Hospital, Predictive Analytics"}, "20": {"organization_num_employees_enum": "11-50"}, "21": {"organization_last_funding_type": "Seed"}, "22": {"organization_revenue_range": "\u2014"}, "23": {"organization_funding_total": "R$10,000,000"}, "24": {"organization_last_funding_at": "May 20, 2021"}, "25": {"organization_last_funding_total": "R$10,000,000"}, "26": {"organization_private_tags": "\u2014"}, "27": {"add_column": ""}, "length": 28, "prevObject": {"0": {"__ngContext__": 914082}, "1": {"__ngContext__": 915440}, "2": {"__ngContext__": 915460}, "3": {"__ngContext__": 915468}, "4": {"__ngContext__": 915476}, "5": {"__ngContext__": 915492}, "6": {"__ngContext__": 915510}, "7": {"__ngContext__": 915531}, "8": {"__ngContext__": 915547}, "9": {"__ngContext__": 915558}, "10": {"__ngContext__": 915571}, "11": {"__ngContext__": 915581}, "12": {"__ngContext__": 915591}, "13": {"__ngContext__": 915601}, "14": {"__ngContext__": 915611}, "15": {"__ngContext__": 915621}, "16": {"__ngContext__": 915631}, "17": {"__ngContext__": 915641}, "18": {"__ngContext__": 915651}, "19": {"__ngContext__": 915661}, "20": {"__ngContext__": 915685}, "21": {"__ngContext__": 915693}, "22": {"__ngContext__": 915701}, "23": {"__ngContext__": 915711}, "24": {"__ngContext__": 915719}, "25": {"__ngContext__": 915727}, "26": {"__ngContext__": 915735}, "27": {"__ngContext__": 914082}, "length": 28, "prevObject": {"0": {"__ngContext__": 914082, "__zone_symbol__clickfalse": [{"type": "eventTask", "state": "scheduled", "source": "HTMLElement.addEventListener:click", "zone": "angular", "runCount": 0}], "__zone_symbol__mouseoverfalse": [{"type": "eventTask", "state": "scheduled", "source": "HTMLElement.addEventListener:mouseover", "zone": "angular", "runCount": 0}], "__zone_symbol__mouseoutfalse": [{"type": "eventTask", "state": "scheduled", "source": "HTMLElement.addEventListener:mouseout", "zone": "angular", "runCount": 0}]}, "length": 1}}}, {"0": {"select": ""}, "1": {"identifier": "Nicholas Domene"}, "2": {"organization_founded_on": "Nov 11, 2016"}, "3": {"organization_operating_status": "Active"}, "4": {"organization": "Insider Store"}, "5": {"job_titles": "\u2014"}, "6": {"organization_locations": "S\u00e3o Paulo, Sao Paulo, Brazil"}, "7": {"linkedin": "https://linkedin.com/in/nicholas-domene"}, "8": {"job_departments": "Information Technology"}, "9": {"job_levels": "Non-Management"}, "10": {"private_work_emails": "\u2014"}, "11": {"private_personal_emails": "\u2014"}, "12": {"private_work_phones": "\u2014"}, "13": {"private_personal_phones": "\u2014"}, "14": {"num_private_contact_items": "\u2014"}, "15": {"num_emails": "1"}, "16": {"num_phones": "\u2014"}, "17": {"max_email_confidence": "Unknown"}, "18": {"max_phone_confidence": "\u2014"}, "19": {"organization_categories": "E-Commerce, Fashion, Retail"}, "20": {"organization_num_employees_enum": "51-100"}, "21": {"organization_last_funding_type": "Debt Financing"}, "22": {"organization_revenue_range": "\u2014"}, "23": {"organization_funding_total": "R$12,000,000"}, "24": {"organization_last_funding_at": "Aug 9, 2021"}, "25": {"organization_last_funding_total": "R$12,000,000"}, "26": {"organization_private_tags": "\u2014"}, "27": {"add_column": ""}, "length": 28, "prevObject": {"0": {"__ngContext__": 915748}, "1": {"__ngContext__": 915799}, "2": {"__ngContext__": 915819}, "3": {"__ngContext__": 915827}, "4": {"__ngContext__": 915835}, "5": {"__ngContext__": 915851}, "6": {"__ngContext__": 915864}, "7": {"__ngContext__": 915885}, "8": {"__ngContext__": 915901}, "9": {"__ngContext__": 915914}, "10": {"__ngContext__": 915927}, "11": {"__ngContext__": 915937}, "12": {"__ngContext__": 915947}, "13": {"__ngContext__": 915957}, "14": {"__ngContext__": 915967}, "15": {"__ngContext__": 915977}, "16": {"__ngContext__": 915987}, "17": {"__ngContext__": 915997}, "18": {"__ngContext__": 916007}, "19": {"__ngContext__": 916017}, "20": {"__ngContext__": 916038}, "21": {"__ngContext__": 916046}, "22": {"__ngContext__": 916054}, "23": {"__ngContext__": 916064}, "24": {"__ngContext__": 916072}, "25": {"__ngContext__": 916080}, "26": {"__ngContext__": 916088}, "27": {"__ngContext__": 915748}, "length": 28, "prevObject": {"0": {"__ngContext__": 915748, "__zone_symbol__clickfalse": [{"type": "eventTask", "state": "scheduled", "source": "HTMLElement.addEventListener:click", "zone": "angular", "runCount": 0}], "__zone_symbol__mouseoverfalse": [{"type": "eventTask", "state": "scheduled", "source": "HTMLElement.addEventListener:mouseover", "zone": "angular", "runCount": 0}], "__zone_symbol__mouseoutfalse": [{"type": "eventTask", "state": "scheduled", "source": "HTMLElement.addEventListener:mouseout", "zone": "angular", "runCount": 0}]}, "length": 1}}}, {"0": {"select": ""}, "1": {"identifier": "Viviana David"}, "2": {"organization_founded_on": "Jan 10, 2013"}, "3": {"organization_operating_status": "Active"}, "4": {"organization": "Intellibrand"}, "5": {"job_titles": "\u2014"}, "6": {"organization_locations": "S\u00e3o Paulo, Sao Paulo, Brazil"}, "7": {"linkedin": "https://linkedin.com/in/viviana-david-90888637"}, "8": {"job_departments": "Operations"}, "9": {"job_levels": "Manager"}, "10": {"private_work_emails": "\u2014"}, "11": {"private_personal_emails": "\u2014"}, "12": {"private_work_phones": "\u2014"}, "13": {"private_personal_phones": "\u2014"}, "14": {"num_private_contact_items": "\u2014"}, "15": {"num_emails": "2"}, "16": {"num_phones": "\u2014"}, "17": {"max_email_confidence": "Unknown"}, "18": {"max_phone_confidence": "\u2014"}, "19": {"organization_categories": "Advertising, Analytics, Big Data, E-Commerce"}, "20": {"organization_num_employees_enum": "11-50"}, "21": {"organization_last_funding_type": "Venture - Series Unknown"}, "22": {"organization_revenue_range": "$1M to $10M"}, "23": {"organization_funding_total": "R$5,000,000"}, "24": {"organization_last_funding_at": "Jun 30, 2017"}, "25": {"organization_last_funding_total": "R$5,000,000"}, "26": {"organization_private_tags": "\u2014"}, "27": {"add_column": ""}, "length": 28, "prevObject": {"0": {"__ngContext__": 915753}, "1": {"__ngContext__": 916127}, "2": {"__ngContext__": 916147}, "3": {"__ngContext__": 916155}, "4": {"__ngContext__": 916163}, "5": {"__ngContext__": 916179}, "6": {"__ngContext__": 916192}, "7": {"__ngContext__": 916213}, "8": {"__ngContext__": 916229}, "9": {"__ngContext__": 916242}, "10": {"__ngContext__": 916255}, "11": {"__ngContext__": 916265}, "12": {"__ngContext__": 916275}, "13": {"__ngContext__": 916285}, "14": {"__ngContext__": 916295}, "15": {"__ngContext__": 916305}, "16": {"__ngContext__": 916315}, "17": {"__ngContext__": 916325}, "18": {"__ngContext__": 916335}, "19": {"__ngContext__": 916345}, "20": {"__ngContext__": 916369}, "21": {"__ngContext__": 916377}, "22": {"__ngContext__": 916385}, "23": {"__ngContext__": 916393}, "24": {"__ngContext__": 916401}, "25": {"__ngContext__": 916409}, "26": {"__ngContext__": 916417}, "27": {"__ngContext__": 915753}, "length": 28, "prevObject": {"0": {"__ngContext__": 915753, "__zone_symbol__clickfalse": [{"type": "eventTask", "state": "scheduled", "source": "HTMLElement.addEventListener:click", "zone": "angular", "runCount": 0}], "__zone_symbol__mouseoverfalse": [{"type": "eventTask", "state": "scheduled", "source": "HTMLElement.addEventListener:mouseover", "zone": "angular", "runCount": 0}], "__zone_symbol__mouseoutfalse": [{"type": "eventTask", "state": "scheduled", "source": "HTMLElement.addEventListener:mouseout", "zone": "angular", "runCount": 0}]}, "length": 1}}}, {"0": {"select": ""}, "1": {"identifier": "Dave Christenberry"}, "2": {"organization_founded_on": "Oct 5, 2017"}, "3": {"organization_operating_status": "Active"}, "4": {"organization": "Woof"}, "5": {"job_titles": "Sales Professional"}, "6": {"organization_locations": "S\u00e3o Paulo, Sao Paulo, Brazil"}, "7": {"linkedin": "https://linkedin.com/in/dave-christenberry-9847373"}, "8": {"job_departments": "\u2014"}, "9": {"job_levels": "Non-Management"}, "10": {"private_work_emails": "\u2014"}, "11": {"private_personal_emails": "\u2014"}, "12": {"private_work_phones": "\u2014"}, "13": {"private_personal_phones": "\u2014"}, "14": {"num_private_contact_items": "\u2014"}, "15": {"num_emails": "1"}, "16": {"num_phones": "\u2014"}, "17": {"max_email_confidence": "Unknown"}, "18": {"max_phone_confidence": "\u2014"}, "19": {"organization_categories": "Apps, E-Commerce, Location Based Services, Marketplace, Mobile Apps, Mobile Payments"}, "20": {"organization_num_employees_enum": "11-50"}, "21": {"organization_last_funding_type": "Venture - Series Unknown"}, "22": {"organization_revenue_range": "\u2014"}, "23": {"organization_funding_total": "$1,975,118"}, "24": {"organization_last_funding_at": "Feb 1, 2022"}, "25": {"organization_last_funding_total": "R$6,200,000"}, "26": {"organization_private_tags": "\u2014"}, "27": {"add_column": ""}, "length": 28, "prevObject": {"0": {"__ngContext__": 915758}, "1": {"__ngContext__": 916456}, "2": {"__ngContext__": 916476}, "3": {"__ngContext__": 916484}, "4": {"__ngContext__": 916492}, "5": {"__ngContext__": 916508}, "6": {"__ngContext__": 916523}, "7": {"__ngContext__": 916544}, "8": {"__ngContext__": 916560}, "9": {"__ngContext__": 916571}, "10": {"__ngContext__": 916584}, "11": {"__ngContext__": 916594}, "12": {"__ngContext__": 916604}, "13": {"__ngContext__": 916614}, "14": {"__ngContext__": 916624}, "15": {"__ngContext__": 916634}, "16": {"__ngContext__": 916644}, "17": {"__ngContext__": 916654}, "18": {"__ngContext__": 916664}, "19": {"__ngContext__": 916674}, "20": {"__ngContext__": 916704}, "21": {"__ngContext__": 916712}, "22": {"__ngContext__": 916720}, "23": {"__ngContext__": 916730}, "24": {"__ngContext__": 916738}, "25": {"__ngContext__": 916746}, "26": {"__ngContext__": 916754}, "27": {"__ngContext__": 915758}, "length": 28, "prevObject": {"0": {"__ngContext__": 915758, "__zone_symbol__clickfalse": [{"type": "eventTask", "state": "scheduled", "source": "HTMLElement.addEventListener:click", "zone": "angular", "runCount": 0}], "__zone_symbol__mouseoverfalse": [{"type": "eventTask", "state": "scheduled", "source": "HTMLElement.addEventListener:mouseover", "zone": "angular", "runCount": 0}], "__zone_symbol__mouseoutfalse": [{"type": "eventTask", "state": "scheduled", "source": "HTMLElement.addEventListener:mouseout", "zone": "angular", "runCount": 0}]}, "length": 1}}}, {"0": {"select": ""}, "1": {"identifier": "Susan Waters"}, "2": {"organization_founded_on": "Oct 5, 2017"}, "3": {"organization_operating_status": "Active"}, "4": {"organization": "Woof"}, "5": {"job_titles": "Marketing Professional"}, "6": {"organization_locations": "S\u00e3o Paulo, Sao Paulo, Brazil"}, "7": {"linkedin": "https://linkedin.com/in/susan-waters-a9b8a483"}, "8": {"job_departments": "\u2014"}, "9": {"job_levels": "Non-Management"}, "10": {"private_work_emails": "\u2014"}, "11": {"private_personal_emails": "\u2014"}, "12": {"private_work_phones": "\u2014"}, "13": {"private_personal_phones": "\u2014"}, "14": {"num_private_contact_items": "\u2014"}, "15": {"num_emails": "1"}, "16": {"num_phones": "\u2014"}, "17": {"max_email_confidence": "Unknown"}, "18": {"max_phone_confidence": "\u2014"}, "19": {"organization_categories": "Apps, E-Commerce, Location Based Services, Marketplace, Mobile Apps, Mobile Payments"}, "20": {"organization_num_employees_enum": "11-50"}, "21": {"organization_last_funding_type": "Venture - Series Unknown"}, "22": {"organization_revenue_range": "\u2014"}, "23": {"organization_funding_total": "$1,975,118"}, "24": {"organization_last_funding_at": "Feb 1, 2022"}, "25": {"organization_last_funding_total": "R$6,200,000"}, "26": {"organization_private_tags": "\u2014"}, "27": {"add_column": ""}, "length": 28, "prevObject": {"0": {"__ngContext__": 915763}, "1": {"__ngContext__": 916793}, "2": {"__ngContext__": 916813}, "3": {"__ngContext__": 916821}, "4": {"__ngContext__": 916829}, "5": {"__ngContext__": 916845}, "6": {"__ngContext__": 916860}, "7": {"__ngContext__": 916881}, "8": {"__ngContext__": 916897}, "9": {"__ngContext__": 916908}, "10": {"__ngContext__": 916921}, "11": {"__ngContext__": 916931}, "12": {"__ngContext__": 916941}, "13": {"__ngContext__": 916951}, "14": {"__ngContext__": 916961}, "15": {"__ngContext__": 916971}, "16": {"__ngContext__": 916981}, "17": {"__ngContext__": 916991}, "18": {"__ngContext__": 917001}, "19": {"__ngContext__": 917011}, "20": {"__ngContext__": 917041}, "21": {"__ngContext__": 917049}, "22": {"__ngContext__": 917057}, "23": {"__ngContext__": 917067}, "24": {"__ngContext__": 917075}, "25": {"__ngContext__": 917083}, "26": {"__ngContext__": 917091}, "27": {"__ngContext__": 915763}, "length": 28, "prevObject": {"0": {"__ngContext__": 915763, "__zone_symbol__clickfalse": [{"type": "eventTask", "state": "scheduled", "source": "HTMLElement.addEventListener:click", "zone": "angular", "runCount": 0}], "__zone_symbol__mouseoverfalse": [{"type": "eventTask", "state": "scheduled", "source": "HTMLElement.addEventListener:mouseover", "zone": "angular", "runCount": 0}], "__zone_symbol__mouseoutfalse": [{"type": "eventTask", "state": "scheduled", "source": "HTMLElement.addEventListener:mouseout", "zone": "angular", "runCount": 0}]}, "length": 1}}}, {"0": {"select": ""}, "1": {"identifier": "Claire Putman"}, "2": {"organization_founded_on": "Oct 5, 2017"}, "3": {"organization_operating_status": "Active"}, "4": {"organization": "Woof"}, "5": {"job_titles": "Health Professional"}, "6": {"organization_locations": "S\u00e3o Paulo, Sao Paulo, Brazil"}, "7": {"linkedin": "https://linkedin.com/in/claire-putman-a860778b"}, "8": {"job_departments": "\u2014"}, "9": {"job_levels": "Non-Management"}, "10": {"private_work_emails": "\u2014"}, "11": {"private_personal_emails": "\u2014"}, "12": {"private_work_phones": "\u2014"}, "13": {"private_personal_phones": "\u2014"}, "14": {"num_private_contact_items": "\u2014"}, "15": {"num_emails": "1"}, "16": {"num_phones": "\u2014"}, "17": {"max_email_confidence": "Unknown"}, "18": {"max_phone_confidence": "\u2014"}, "19": {"organization_categories": "Apps, E-Commerce, Location Based Services, Marketplace, Mobile Apps, Mobile Payments"}, "20": {"organization_num_employees_enum": "11-50"}, "21": {"organization_last_funding_type": "Venture - Series Unknown"}, "22": {"organization_revenue_range": "\u2014"}, "23": {"organization_funding_total": "$1,975,118"}, "24": {"organization_last_funding_at": "Feb 1, 2022"}, "25": {"organization_last_funding_total": "R$6,200,000"}, "26": {"organization_private_tags": "\u2014"}, "27": {"add_column": ""}, "length": 28, "prevObject": {"0": {"__ngContext__": 915768}, "1": {"__ngContext__": 917130}, "2": {"__ngContext__": 917150}, "3": {"__ngContext__": 917158}, "4": {"__ngContext__": 917166}, "5": {"__ngContext__": 917182}, "6": {"__ngContext__": 917197}, "7": {"__ngContext__": 917218}, "8": {"__ngContext__": 917234}, "9": {"__ngContext__": 917245}, "10": {"__ngContext__": 917258}, "11": {"__ngContext__": 917268}, "12": {"__ngContext__": 917278}, "13": {"__ngContext__": 917288}, "14": {"__ngContext__": 917298}, "15": {"__ngContext__": 917308}, "16": {"__ngContext__": 917318}, "17": {"__ngContext__": 917328}, "18": {"__ngContext__": 917338}, "19": {"__ngContext__": 917348}, "20": {"__ngContext__": 917378}, "21": {"__ngContext__": 917386}, "22": {"__ngContext__": 917394}, "23": {"__ngContext__": 917404}, "24": {"__ngContext__": 917412}, "25": {"__ngContext__": 917420}, "26": {"__ngContext__": 917428}, "27": {"__ngContext__": 915768}, "length": 28, "prevObject": {"0": {"__ngContext__": 915768, "__zone_symbol__clickfalse": [{"type": "eventTask", "state": "scheduled", "source": "HTMLElement.addEventListener:click", "zone": "angular", "runCount": 0}], "__zone_symbol__mouseoverfalse": [{"type": "eventTask", "state": "scheduled", "source": "HTMLElement.addEventListener:mouseover", "zone": "angular", "runCount": 0}], "__zone_symbol__mouseoutfalse": [{"type": "eventTask", "state": "scheduled", "source": "HTMLElement.addEventListener:mouseout", "zone": "angular", "runCount": 0}]}, "length": 1}}}]