[{"0": {"select": ""}, "1": {"identifier": "QuePlan"}, "2": {"last_key_employee_change_date": "\u2014"}, "3": {"growth_insight_indicator": "\u2014"}, "4": {"last_funding_at": "\u2014"}, "5": {"last_funding_type": "\u2014"}, "6": {"contact_job_departments": "\u2014"}, "7": {"num_contacts": "\u2014"}, "8": {"num_employees_enum": "11-50"}, "9": {"founded_on": "2020"}, "10": {"categories": "Insurance, Internet, Telecommunications"}, "11": {"location_identifiers": "Guadalajara, Jalisco, Mexico"}, "12": {"short_description": "QuePlan specializes in telecommunications and insurance services."}, "13": {"rank_org_company": "968,181"}, "14": {"location_group_identifiers": "Latin America"}, "15": {"linkedin": "https://www.linkedin.com/company/queplanmx"}, "16": {"contact_email": "queplan20@gmail.com"}, "17": {"phone_number": "+52 55 8950 9428"}, "18": {"description": "\u2014"}, "19": {"founder_identifiers": "\u2014"}, "20": {"num_founders": "\u2014"}, "21": {"add_column": ""}, "length": 22, "prevObject": {"0": {"__ngContext__": 3851832}, "1": {"__ngContext__": 3851879}, "2": {"__ngContext__": 3851907}, "3": {"__ngContext__": 3851917}, "4": {"__ngContext__": 3851927}, "5": {"__ngContext__": 3851937}, "6": {"__ngContext__": 3851947}, "7": {"__ngContext__": 3851958}, "8": {"__ngContext__": 3851968}, "9": {"__ngContext__": 3851976}, "10": {"__ngContext__": 3851986}, "11": {"__ngContext__": 3852007}, "12": {"__ngContext__": 3852028}, "13": {"__ngContext__": 3852038}, "14": {"__ngContext__": 3852046}, "15": {"__ngContext__": 3852061}, "16": {"__ngContext__": 3852076}, "17": {"__ngContext__": 3852088}, "18": {"__ngContext__": 3852100}, "19": {"__ngContext__": 3852110}, "20": {"__ngContext__": 3852123}, "21": {"__ngContext__": 3851832}, "length": 22, "prevObject": {"0": {"__ngContext__": 3851832, "__zone_symbol__clickfalse": [{"type": "eventTask", "state": "scheduled", "source": "HTMLElement.addEventListener:click", "zone": "angular", "runCount": 0}], "__zone_symbol__mouseoverfalse": [{"type": "eventTask", "state": "scheduled", "source": "HTMLElement.addEventListener:mouseover", "zone": "angular", "runCount": 0}], "__zone_symbol__mouseoutfalse": [{"type": "eventTask", "state": "scheduled", "source": "HTMLElement.addEventListener:mouseout", "zone": "angular", "runCount": 0}]}, "length": 1}}}, {"0": {"select": ""}, "1": {"identifier": "Housale"}, "2": {"last_key_employee_change_date": "\u2014"}, "3": {"growth_insight_indicator": "\u2014"}, "4": {"last_funding_at": "\u2014"}, "5": {"last_funding_type": "\u2014"}, "6": {"contact_job_departments": "\u2014"}, "7": {"num_contacts": "\u2014"}, "8": {"num_employees_enum": "1-10"}, "9": {"founded_on": "2020"}, "10": {"categories": "Internet, Real Estate, Sales"}, "11": {"location_identifiers": "Cuauht\u00e9moc, Colima, Mexico"}, "12": {"short_description": "Housale is involved in the real estate market."}, "13": {"rank_org_company": "972,477"}, "14": {"location_group_identifiers": "Latin America"}, "15": {"linkedin": "https://www.linkedin.com/company/housale-mx"}, "16": {"contact_email": "clientes@housale.mx"}, "17": {"phone_number": "+52 555 204 3919"}, "18": {"description": "Housale gives customers the advice and the tools they need to carry out the sales process directly. They explain the reason for the value of customer property. They provide feedback on customer property in real-time. After each visit, they ask the interested buyer how it went. This information will be useful when selling the property. They provide online management of the entire process, professional photos of their property, the ad will be in the real estate portals, premium positioning in the portals, selecting the best buyers, and legal advice."}, "19": {"founder_identifiers": "\u2014"}, "20": {"num_founders": "\u2014"}, "21": {"add_column": ""}, "length": 22, "prevObject": {"0": {"__ngContext__": 3851837}, "1": {"__ngContext__": 3852153}, "2": {"__ngContext__": 3852181}, "3": {"__ngContext__": 3852191}, "4": {"__ngContext__": 3852201}, "5": {"__ngContext__": 3852211}, "6": {"__ngContext__": 3852221}, "7": {"__ngContext__": 3852232}, "8": {"__ngContext__": 3852242}, "9": {"__ngContext__": 3852250}, "10": {"__ngContext__": 3852260}, "11": {"__ngContext__": 3852281}, "12": {"__ngContext__": 3852302}, "13": {"__ngContext__": 3852312}, "14": {"__ngContext__": 3852320}, "15": {"__ngContext__": 3852335}, "16": {"__ngContext__": 3852350}, "17": {"__ngContext__": 3852362}, "18": {"__ngContext__": 3852374}, "19": {"__ngContext__": 3852384}, "20": {"__ngContext__": 3852397}, "21": {"__ngContext__": 3851837}, "length": 22, "prevObject": {"0": {"__ngContext__": 3851837, "__zone_symbol__clickfalse": [{"type": "eventTask", "state": "scheduled", "source": "HTMLElement.addEventListener:click", "zone": "angular", "runCount": 0}], "__zone_symbol__mouseoverfalse": [{"type": "eventTask", "state": "scheduled", "source": "HTMLElement.addEventListener:mouseover", "zone": "angular", "runCount": 0}], "__zone_symbol__mouseoutfalse": [{"type": "eventTask", "state": "scheduled", "source": "HTMLElement.addEventListener:mouseout", "zone": "angular", "runCount": 0}]}, "length": 1}}}, {"0": {"select": ""}, "1": {"identifier": "Aloux"}, "2": {"last_key_employee_change_date": "\u2014"}, "3": {"growth_insight_indicator": "\u2014"}, "4": {"last_funding_at": "\u2014"}, "5": {"last_funding_type": "\u2014"}, "6": {"contact_job_departments": "\u2014"}, "7": {"num_contacts": "\u2014"}, "8": {"num_employees_enum": "11-50"}, "9": {"founded_on": "2020"}, "10": {"categories": "Information Technology, Marketing, Mobile Apps, Social Media, Software, UX Design, Web Design, Web Development"}, "11": {"location_identifiers": "Mexico City, Distrito Federal, Mexico"}, "12": {"short_description": "Aloux is an IT company that provides brand design, UX design, content strategy, web page development, and mobile app development services."}, "13": {"rank_org_company": "977,701"}, "14": {"location_group_identifiers": "Latin America"}, "15": {"linkedin": "https://www.linkedin.com/company/aloux-mx"}, "16": {"contact_email": "contacto@aloux.mx"}, "17": {"phone_number": "52 56 3458 3951"}, "18": {"description": "\u2014"}, "19": {"founder_identifiers": "\u2014"}, "20": {"num_founders": "\u2014"}, "21": {"add_column": ""}, "length": 22, "prevObject": {"0": {"__ngContext__": 3851842}, "1": {"__ngContext__": 3852427}, "2": {"__ngContext__": 3852455}, "3": {"__ngContext__": 3852465}, "4": {"__ngContext__": 3852475}, "5": {"__ngContext__": 3852485}, "6": {"__ngContext__": 3852495}, "7": {"__ngContext__": 3852506}, "8": {"__ngContext__": 3852516}, "9": {"__ngContext__": 3852524}, "10": {"__ngContext__": 3852534}, "11": {"__ngContext__": 3852570}, "12": {"__ngContext__": 3852591}, "13": {"__ngContext__": 3852601}, "14": {"__ngContext__": 3852609}, "15": {"__ngContext__": 3852624}, "16": {"__ngContext__": 3852639}, "17": {"__ngContext__": 3852651}, "18": {"__ngContext__": 3852663}, "19": {"__ngContext__": 3852673}, "20": {"__ngContext__": 3852686}, "21": {"__ngContext__": 3851842}, "length": 22, "prevObject": {"0": {"__ngContext__": 3851842, "__zone_symbol__clickfalse": [{"type": "eventTask", "state": "scheduled", "source": "HTMLElement.addEventListener:click", "zone": "angular", "runCount": 0}], "__zone_symbol__mouseoverfalse": [{"type": "eventTask", "state": "scheduled", "source": "HTMLElement.addEventListener:mouseover", "zone": "angular", "runCount": 0}], "__zone_symbol__mouseoutfalse": [{"type": "eventTask", "state": "scheduled", "source": "HTMLElement.addEventListener:mouseout", "zone": "angular", "runCount": 0}]}, "length": 1}}}, {"0": {"select": ""}, "1": {"identifier": "Kanaus"}, "2": {"last_key_employee_change_date": "\u2014"}, "3": {"growth_insight_indicator": "\u2014"}, "4": {"last_funding_at": "\u2014"}, "5": {"last_funding_type": "\u2014"}, "6": {"contact_job_departments": "\u2014"}, "7": {"num_contacts": "\u2014"}, "8": {"num_employees_enum": "51-100"}, "9": {"founded_on": "2020"}, "10": {"categories": "E-Commerce, Fashion, Textiles"}, "11": {"location_identifiers": "Tulancingo, Hidalgo, Mexico"}, "12": {"short_description": "Kanaus sells coats, jackets, and medical uniforms."}, "13": {"rank_org_company": "980,204"}, "14": {"location_group_identifiers": "Latin America"}, "15": {"linkedin": "https://www.linkedin.com/company/kanaus"}, "16": {"contact_email": "info@kanaus.com"}, "17": {"phone_number": "+52 7751464749"}, "18": {"description": "\u2014"}, "19": {"founder_identifiers": "\u2014"}, "20": {"num_founders": "\u2014"}, "21": {"add_column": ""}, "length": 22, "prevObject": {"0": {"__ngContext__": 3851847}, "1": {"__ngContext__": 3852716}, "2": {"__ngContext__": 3852744}, "3": {"__ngContext__": 3852754}, "4": {"__ngContext__": 3852764}, "5": {"__ngContext__": 3852774}, "6": {"__ngContext__": 3852784}, "7": {"__ngContext__": 3852795}, "8": {"__ngContext__": 3852805}, "9": {"__ngContext__": 3852813}, "10": {"__ngContext__": 3852823}, "11": {"__ngContext__": 3852844}, "12": {"__ngContext__": 3852865}, "13": {"__ngContext__": 3852875}, "14": {"__ngContext__": 3852883}, "15": {"__ngContext__": 3852898}, "16": {"__ngContext__": 3852913}, "17": {"__ngContext__": 3852925}, "18": {"__ngContext__": 3852937}, "19": {"__ngContext__": 3852947}, "20": {"__ngContext__": 3852960}, "21": {"__ngContext__": 3851847}, "length": 22, "prevObject": {"0": {"__ngContext__": 3851847, "__zone_symbol__clickfalse": [{"type": "eventTask", "state": "scheduled", "source": "HTMLElement.addEventListener:click", "zone": "angular", "runCount": 0}], "__zone_symbol__mouseoverfalse": [{"type": "eventTask", "state": "scheduled", "source": "HTMLElement.addEventListener:mouseover", "zone": "angular", "runCount": 0}], "__zone_symbol__mouseoutfalse": [{"type": "eventTask", "state": "scheduled", "source": "HTMLElement.addEventListener:mouseout", "zone": "angular", "runCount": 0}]}, "length": 1}}}, {"0": {"select": ""}, "1": {"identifier": "EntoPro"}, "2": {"last_key_employee_change_date": "\u2014"}, "3": {"growth_insight_indicator": "\u2014"}, "4": {"last_funding_at": "\u2014"}, "5": {"last_funding_type": "\u2014"}, "6": {"contact_job_departments": "\u2014"}, "7": {"num_contacts": "\u2014"}, "8": {"num_employees_enum": "1-10"}, "9": {"founded_on": "2020"}, "10": {"categories": "AgTech, Biotechnology, Farming"}, "11": {"location_identifiers": "Bogot\u00e1, Distrito Especial, Colombia"}, "12": {"short_description": "EntoPro is a technology company that develops the formulation and implementation of production systems to support insect farming."}, "13": {"rank_org_company": "982,252"}, "14": {"location_group_identifiers": "Latin America"}, "15": {"linkedin": "https://www.linkedin.com/company/entopro-sas/"}, "16": {"contact_email": "info@entopro.com.co"}, "17": {"phone_number": "+57-324-543-9872"}, "18": {"description": "\u2014"}, "19": {"founder_identifiers": "\u2014"}, "20": {"num_founders": "\u2014"}, "21": {"add_column": ""}, "length": 22, "prevObject": {"0": {"__ngContext__": 3851852}, "1": {"__ngContext__": 3852990}, "2": {"__ngContext__": 3853018}, "3": {"__ngContext__": 3853028}, "4": {"__ngContext__": 3853038}, "5": {"__ngContext__": 3853048}, "6": {"__ngContext__": 3853058}, "7": {"__ngContext__": 3853069}, "8": {"__ngContext__": 3853079}, "9": {"__ngContext__": 3853087}, "10": {"__ngContext__": 3853097}, "11": {"__ngContext__": 3853118}, "12": {"__ngContext__": 3853139}, "13": {"__ngContext__": 3853149}, "14": {"__ngContext__": 3853157}, "15": {"__ngContext__": 3853172}, "16": {"__ngContext__": 3853187}, "17": {"__ngContext__": 3853199}, "18": {"__ngContext__": 3853211}, "19": {"__ngContext__": 3853221}, "20": {"__ngContext__": 3853234}, "21": {"__ngContext__": 3851852}, "length": 22, "prevObject": {"0": {"__ngContext__": 3851852, "__zone_symbol__clickfalse": [{"type": "eventTask", "state": "scheduled", "source": "HTMLElement.addEventListener:click", "zone": "angular", "runCount": 0}], "__zone_symbol__mouseoverfalse": [{"type": "eventTask", "state": "scheduled", "source": "HTMLElement.addEventListener:mouseover", "zone": "angular", "runCount": 0}], "__zone_symbol__mouseoutfalse": [{"type": "eventTask", "state": "scheduled", "source": "HTMLElement.addEventListener:mouseout", "zone": "angular", "runCount": 0}]}, "length": 1}}}, {"0": {"select": ""}, "1": {"identifier": "Educaci\u00f3n Colectiva"}, "2": {"last_key_employee_change_date": "\u2014"}, "3": {"growth_insight_indicator": "\u2014"}, "4": {"last_funding_at": "\u2014"}, "5": {"last_funding_type": "\u2014"}, "6": {"contact_job_departments": "\u2014"}, "7": {"num_contacts": "\u2014"}, "8": {"num_employees_enum": "11-50"}, "9": {"founded_on": "2020"}, "10": {"categories": "Education, Events, Social, Training"}, "11": {"location_identifiers": "Guadalajara, Jalisco, Mexico"}, "12": {"short_description": "Educaci\u00f3n Colectiva offers education, social, work, and life training programs for workers."}, "13": {"rank_org_company": "994,039"}, "14": {"location_group_identifiers": "Latin America"}, "15": {"linkedin": "https://www.linkedin.com/company/educaci%C3%B3n-colectiva/"}, "16": {"contact_email": "contacto@educacioncolectiva.com"}, "17": {"phone_number": "+52 3334150431"}, "18": {"description": "\u2014"}, "19": {"founder_identifiers": "\u2014"}, "20": {"num_founders": "\u2014"}, "21": {"add_column": ""}, "length": 22, "prevObject": {"0": {"__ngContext__": 3853244}, "1": {"__ngContext__": 3853289}, "2": {"__ngContext__": 3853317}, "3": {"__ngContext__": 3853327}, "4": {"__ngContext__": 3853337}, "5": {"__ngContext__": 3853347}, "6": {"__ngContext__": 3853357}, "7": {"__ngContext__": 3853368}, "8": {"__ngContext__": 3853378}, "9": {"__ngContext__": 3853386}, "10": {"__ngContext__": 3853396}, "11": {"__ngContext__": 3853420}, "12": {"__ngContext__": 3853441}, "13": {"__ngContext__": 3853451}, "14": {"__ngContext__": 3853459}, "15": {"__ngContext__": 3853474}, "16": {"__ngContext__": 3853489}, "17": {"__ngContext__": 3853501}, "18": {"__ngContext__": 3853513}, "19": {"__ngContext__": 3853523}, "20": {"__ngContext__": 3853536}, "21": {"__ngContext__": 3853244}, "length": 22, "prevObject": {"0": {"__ngContext__": 3853244, "__zone_symbol__clickfalse": [{"type": "eventTask", "state": "scheduled", "source": "HTMLElement.addEventListener:click", "zone": "angular", "runCount": 0}], "__zone_symbol__mouseoverfalse": [{"type": "eventTask", "state": "scheduled", "source": "HTMLElement.addEventListener:mouseover", "zone": "angular", "runCount": 0}], "__zone_symbol__mouseoutfalse": [{"type": "eventTask", "state": "scheduled", "source": "HTMLElement.addEventListener:mouseout", "zone": "angular", "runCount": 0}]}, "length": 1}}}, {"0": {"select": ""}, "1": {"identifier": "IkiGo"}, "2": {"last_key_employee_change_date": "\u2014"}, "3": {"growth_insight_indicator": "\u2014"}, "4": {"last_funding_at": "\u2014"}, "5": {"last_funding_type": "\u2014"}, "6": {"contact_job_departments": "\u2014"}, "7": {"num_contacts": "\u2014"}, "8": {"num_employees_enum": "11-50"}, "9": {"founded_on": "2020"}, "10": {"categories": "Business Intelligence, Consulting, Information Technology"}, "11": {"location_identifiers": "Buenos Aires, Distrito Federal, Argentina"}, "12": {"short_description": "IkiGo offers digital transformation, agility training, and delivery management services."}, "13": {"rank_org_company": "994,459"}, "14": {"location_group_identifiers": "Latin America"}, "15": {"linkedin": "https://www.linkedin.com/company/ikigoarg"}, "16": {"contact_email": "info@ikigo.biz"}, "17": {"phone_number": "54 9 11 51111782"}, "18": {"description": "\u2014"}, "19": {"founder_identifiers": "Marcela Schwindt, Virginia Veronica"}, "20": {"num_founders": "2"}, "21": {"add_column": ""}, "length": 22, "prevObject": {"0": {"__ngContext__": 3853249}, "1": {"__ngContext__": 3853566}, "2": {"__ngContext__": 3853594}, "3": {"__ngContext__": 3853604}, "4": {"__ngContext__": 3853614}, "5": {"__ngContext__": 3853624}, "6": {"__ngContext__": 3853634}, "7": {"__ngContext__": 3853645}, "8": {"__ngContext__": 3853655}, "9": {"__ngContext__": 3853663}, "10": {"__ngContext__": 3853673}, "11": {"__ngContext__": 3853694}, "12": {"__ngContext__": 3853715}, "13": {"__ngContext__": 3853725}, "14": {"__ngContext__": 3853733}, "15": {"__ngContext__": 3853748}, "16": {"__ngContext__": 3853763}, "17": {"__ngContext__": 3853775}, "18": {"__ngContext__": 3853787}, "19": {"__ngContext__": 3853797}, "20": {"__ngContext__": 3853815}, "21": {"__ngContext__": 3853249}, "length": 22, "prevObject": {"0": {"__ngContext__": 3853249, "__zone_symbol__clickfalse": [{"type": "eventTask", "state": "scheduled", "source": "HTMLElement.addEventListener:click", "zone": "angular", "runCount": 0}], "__zone_symbol__mouseoverfalse": [{"type": "eventTask", "state": "scheduled", "source": "HTMLElement.addEventListener:mouseover", "zone": "angular", "runCount": 0}], "__zone_symbol__mouseoutfalse": [{"type": "eventTask", "state": "scheduled", "source": "HTMLElement.addEventListener:mouseout", "zone": "angular", "runCount": 0}]}, "length": 1}}}, {"0": {"select": ""}, "1": {"identifier": "Superfrutti"}, "2": {"last_key_employee_change_date": "\u2014"}, "3": {"growth_insight_indicator": "\u2014"}, "4": {"last_funding_at": "\u2014"}, "5": {"last_funding_type": "\u2014"}, "6": {"contact_job_departments": "\u2014"}, "7": {"num_contacts": "\u2014"}, "8": {"num_employees_enum": "11-50"}, "9": {"founded_on": "2020"}, "10": {"categories": "Apps, Food Delivery, Software"}, "11": {"location_identifiers": "Bogot\u00e1, Distrito Especial, Colombia"}, "12": {"short_description": "Superfrutti is an application that connects peasants with business owners to sell fruits and vegetables through technology."}, "13": {"rank_org_company": "996,788"}, "14": {"location_group_identifiers": "Latin America"}, "15": {"linkedin": "https://www.linkedin.com/company/superfrutti/"}, "16": {"contact_email": "superfrutticolombia@gmail.com"}, "17": {"phone_number": "\u2014"}, "18": {"description": "\u2014"}, "19": {"founder_identifiers": "\u2014"}, "20": {"num_founders": "\u2014"}, "21": {"add_column": ""}, "length": 22, "prevObject": {"0": {"__ngContext__": 3853254}, "1": {"__ngContext__": 3853843}, "2": {"__ngContext__": 3853871}, "3": {"__ngContext__": 3853881}, "4": {"__ngContext__": 3853891}, "5": {"__ngContext__": 3853901}, "6": {"__ngContext__": 3853911}, "7": {"__ngContext__": 3853922}, "8": {"__ngContext__": 3853932}, "9": {"__ngContext__": 3853940}, "10": {"__ngContext__": 3853950}, "11": {"__ngContext__": 3853971}, "12": {"__ngContext__": 3853992}, "13": {"__ngContext__": 3854002}, "14": {"__ngContext__": 3854010}, "15": {"__ngContext__": 3854025}, "16": {"__ngContext__": 3854040}, "17": {"__ngContext__": 3854052}, "18": {"__ngContext__": 3854063}, "19": {"__ngContext__": 3854073}, "20": {"__ngContext__": 3854086}, "21": {"__ngContext__": 3853254}, "length": 22, "prevObject": {"0": {"__ngContext__": 3853254, "__zone_symbol__clickfalse": [{"type": "eventTask", "state": "scheduled", "source": "HTMLElement.addEventListener:click", "zone": "angular", "runCount": 0}], "__zone_symbol__mouseoverfalse": [{"type": "eventTask", "state": "scheduled", "source": "HTMLElement.addEventListener:mouseover", "zone": "angular", "runCount": 0}], "__zone_symbol__mouseoutfalse": [{"type": "eventTask", "state": "scheduled", "source": "HTMLElement.addEventListener:mouseout", "zone": "angular", "runCount": 0}]}, "length": 1}}}, {"0": {"select": ""}, "1": {"identifier": "Centro Interdisciplinario en Neuropsicolog\u00eda y Salud"}, "2": {"last_key_employee_change_date": "\u2014"}, "3": {"growth_insight_indicator": "\u2014"}, "4": {"last_funding_at": "\u2014"}, "5": {"last_funding_type": "\u2014"}, "6": {"contact_job_departments": "\u2014"}, "7": {"num_contacts": "\u2014"}, "8": {"num_employees_enum": "11-50"}, "9": {"founded_on": "2020"}, "10": {"categories": "Consulting, Health Care, Psychology, Therapeutics, Training"}, "11": {"location_identifiers": "Mexico City, Distrito Federal, Mexico"}, "12": {"short_description": "C.I.E.N.S.A. is a psychology clinic that treats neurodevelopmental disorders for children and adults."}, "13": {"rank_org_company": "1,004,268"}, "14": {"location_group_identifiers": "Latin America"}, "15": {"linkedin": "https://www.linkedin.com/company/ciensa-neuropsicologia"}, "16": {"contact_email": "contacto@neurociensa.com"}, "17": {"phone_number": "+52 5565022277"}, "18": {"description": "\u2014"}, "19": {"founder_identifiers": "\u2014"}, "20": {"num_founders": "\u2014"}, "21": {"add_column": ""}, "length": 22, "prevObject": {"0": {"__ngContext__": 3853259}, "1": {"__ngContext__": 3854116}, "2": {"__ngContext__": 3854144}, "3": {"__ngContext__": 3854154}, "4": {"__ngContext__": 3854164}, "5": {"__ngContext__": 3854174}, "6": {"__ngContext__": 3854184}, "7": {"__ngContext__": 3854195}, "8": {"__ngContext__": 3854205}, "9": {"__ngContext__": 3854213}, "10": {"__ngContext__": 3854223}, "11": {"__ngContext__": 3854250}, "12": {"__ngContext__": 3854271}, "13": {"__ngContext__": 3854281}, "14": {"__ngContext__": 3854289}, "15": {"__ngContext__": 3854304}, "16": {"__ngContext__": 3854319}, "17": {"__ngContext__": 3854331}, "18": {"__ngContext__": 3854343}, "19": {"__ngContext__": 3854353}, "20": {"__ngContext__": 3854366}, "21": {"__ngContext__": 3853259}, "length": 22, "prevObject": {"0": {"__ngContext__": 3853259, "__zone_symbol__clickfalse": [{"type": "eventTask", "state": "scheduled", "source": "HTMLElement.addEventListener:click", "zone": "angular", "runCount": 0}], "__zone_symbol__mouseoverfalse": [{"type": "eventTask", "state": "scheduled", "source": "HTMLElement.addEventListener:mouseover", "zone": "angular", "runCount": 0}], "__zone_symbol__mouseoutfalse": [{"type": "eventTask", "state": "scheduled", "source": "HTMLElement.addEventListener:mouseout", "zone": "angular", "runCount": 0}]}, "length": 1}}}, {"0": {"select": ""}, "1": {"identifier": "Mandarina.bike"}, "2": {"last_key_employee_change_date": "\u2014"}, "3": {"growth_insight_indicator": "\u2014"}, "4": {"last_funding_at": "\u2014"}, "5": {"last_funding_type": "\u2014"}, "6": {"contact_job_departments": "\u2014"}, "7": {"num_contacts": "\u2014"}, "8": {"num_employees_enum": "11-50"}, "9": {"founded_on": "2020"}, "10": {"categories": "Cycling, E-Commerce, Electric Vehicle, Retail"}, "11": {"location_identifiers": "Granjas M\u00e9xico, Distrito Federal, Mexico"}, "12": {"short_description": "Mandarina.bike sells electric scooters, bikes, and motorcycles."}, "13": {"rank_org_company": "1,005,355"}, "14": {"location_group_identifiers": "Latin America"}, "15": {"linkedin": "https://www.linkedin.com/company/mandarina-bike/"}, "16": {"contact_email": "servicio@mandarina.bike"}, "17": {"phone_number": "+52 55 8007 2319"}, "18": {"description": "\u2014"}, "19": {"founder_identifiers": "\u2014"}, "20": {"num_founders": "\u2014"}, "21": {"add_column": ""}, "length": 22, "prevObject": {"0": {"__ngContext__": 3853264}, "1": {"__ngContext__": 3854396}, "2": {"__ngContext__": 3854424}, "3": {"__ngContext__": 3854434}, "4": {"__ngContext__": 3854444}, "5": {"__ngContext__": 3854454}, "6": {"__ngContext__": 3854464}, "7": {"__ngContext__": 3854475}, "8": {"__ngContext__": 3854485}, "9": {"__ngContext__": 3854493}, "10": {"__ngContext__": 3854503}, "11": {"__ngContext__": 3854527}, "12": {"__ngContext__": 3854548}, "13": {"__ngContext__": 3854558}, "14": {"__ngContext__": 3854566}, "15": {"__ngContext__": 3854581}, "16": {"__ngContext__": 3854596}, "17": {"__ngContext__": 3854608}, "18": {"__ngContext__": 3854620}, "19": {"__ngContext__": 3854630}, "20": {"__ngContext__": 3854643}, "21": {"__ngContext__": 3853264}, "length": 22, "prevObject": {"0": {"__ngContext__": 3853264, "__zone_symbol__clickfalse": [{"type": "eventTask", "state": "scheduled", "source": "HTMLElement.addEventListener:click", "zone": "angular", "runCount": 0}], "__zone_symbol__mouseoverfalse": [{"type": "eventTask", "state": "scheduled", "source": "HTMLElement.addEventListener:mouseover", "zone": "angular", "runCount": 0}], "__zone_symbol__mouseoutfalse": [{"type": "eventTask", "state": "scheduled", "source": "HTMLElement.addEventListener:mouseout", "zone": "angular", "runCount": 0}]}, "length": 1}}}, {"0": {"select": ""}, "1": {"identifier": "Land and Building"}, "2": {"last_key_employee_change_date": "\u2014"}, "3": {"growth_insight_indicator": "\u2014"}, "4": {"last_funding_at": "\u2014"}, "5": {"last_funding_type": "\u2014"}, "6": {"contact_job_departments": "\u2014"}, "7": {"num_contacts": "\u2014"}, "8": {"num_employees_enum": "11-50"}, "9": {"founded_on": "2020"}, "10": {"categories": "Media and Entertainment, News, Publishing"}, "11": {"location_identifiers": "Cabo San Lucas, Baja California Sur, Mexico"}, "12": {"short_description": "Land and Building is a magazine publishing company that publishes real estate, property, and building news."}, "13": {"rank_org_company": "1,007,382"}, "14": {"location_group_identifiers": "Latin America"}, "15": {"linkedin": "https://www.linkedin.com/company/landandbuilding"}, "16": {"contact_email": "info@landandbuilding.com"}, "17": {"phone_number": "+52 5514743212"}, "18": {"description": "\u2014"}, "19": {"founder_identifiers": "\u2014"}, "20": {"num_founders": "\u2014"}, "21": {"add_column": ""}, "length": 22, "prevObject": {"0": {"__ngContext__": 3854653}, "1": {"__ngContext__": 3854698}, "2": {"__ngContext__": 3854726}, "3": {"__ngContext__": 3854736}, "4": {"__ngContext__": 3854746}, "5": {"__ngContext__": 3854756}, "6": {"__ngContext__": 3854766}, "7": {"__ngContext__": 3854777}, "8": {"__ngContext__": 3854787}, "9": {"__ngContext__": 3854795}, "10": {"__ngContext__": 3854805}, "11": {"__ngContext__": 3854826}, "12": {"__ngContext__": 3854847}, "13": {"__ngContext__": 3854857}, "14": {"__ngContext__": 3854865}, "15": {"__ngContext__": 3854880}, "16": {"__ngContext__": 3854895}, "17": {"__ngContext__": 3854907}, "18": {"__ngContext__": 3854919}, "19": {"__ngContext__": 3854929}, "20": {"__ngContext__": 3854942}, "21": {"__ngContext__": 3854653}, "length": 22, "prevObject": {"0": {"__ngContext__": 3854653, "__zone_symbol__clickfalse": [{"type": "eventTask", "state": "scheduled", "source": "HTMLElement.addEventListener:click", "zone": "angular", "runCount": 0}], "__zone_symbol__mouseoverfalse": [{"type": "eventTask", "state": "scheduled", "source": "HTMLElement.addEventListener:mouseover", "zone": "angular", "runCount": 0}], "__zone_symbol__mouseoutfalse": [{"type": "eventTask", "state": "scheduled", "source": "HTMLElement.addEventListener:mouseout", "zone": "angular", "runCount": 0}]}, "length": 1}}}, {"0": {"select": ""}, "1": {"identifier": "EcoScience Lab"}, "2": {"last_key_employee_change_date": "\u2014"}, "3": {"growth_insight_indicator": "\u2014"}, "4": {"last_funding_at": "\u2014"}, "5": {"last_funding_type": "\u2014"}, "6": {"contact_job_departments": "\u2014"}, "7": {"num_contacts": "\u2014"}, "8": {"num_employees_enum": "1-10"}, "9": {"founded_on": "2020"}, "10": {"categories": "Agriculture, Biotechnology, Cosmetics, Environmental Consulting"}, "11": {"location_identifiers": "Le\u00f3n, Guanajuato, Mexico"}, "12": {"short_description": "EcoScience Lab is a biotechnology company that provides environmentally friendly scientific solutions."}, "13": {"rank_org_company": "1,015,169"}, "14": {"location_group_identifiers": "Latin America"}, "15": {"linkedin": "https://www.linkedin.com/company/ecosciencelab"}, "16": {"contact_email": "contacto@ecosciencelab.com"}, "17": {"phone_number": "+52 442 233 9188"}, "18": {"description": "\u2014"}, "19": {"founder_identifiers": "\u2014"}, "20": {"num_founders": "\u2014"}, "21": {"add_column": ""}, "length": 22, "prevObject": {"0": {"__ngContext__": 3854658}, "1": {"__ngContext__": 3854972}, "2": {"__ngContext__": 3855000}, "3": {"__ngContext__": 3855010}, "4": {"__ngContext__": 3855020}, "5": {"__ngContext__": 3855030}, "6": {"__ngContext__": 3855040}, "7": {"__ngContext__": 3855051}, "8": {"__ngContext__": 3855061}, "9": {"__ngContext__": 3855069}, "10": {"__ngContext__": 3855079}, "11": {"__ngContext__": 3855103}, "12": {"__ngContext__": 3855124}, "13": {"__ngContext__": 3855134}, "14": {"__ngContext__": 3855142}, "15": {"__ngContext__": 3855157}, "16": {"__ngContext__": 3855172}, "17": {"__ngContext__": 3855184}, "18": {"__ngContext__": 3855196}, "19": {"__ngContext__": 3855206}, "20": {"__ngContext__": 3855219}, "21": {"__ngContext__": 3854658}, "length": 22, "prevObject": {"0": {"__ngContext__": 3854658, "__zone_symbol__clickfalse": [{"type": "eventTask", "state": "scheduled", "source": "HTMLElement.addEventListener:click", "zone": "angular", "runCount": 0}], "__zone_symbol__mouseoverfalse": [{"type": "eventTask", "state": "scheduled", "source": "HTMLElement.addEventListener:mouseover", "zone": "angular", "runCount": 0}], "__zone_symbol__mouseoutfalse": [{"type": "eventTask", "state": "scheduled", "source": "HTMLElement.addEventListener:mouseout", "zone": "angular", "runCount": 0}]}, "length": 1}}}, {"0": {"select": ""}, "1": {"identifier": "Mistiq Tulum"}, "2": {"last_key_employee_change_date": "\u2014"}, "3": {"growth_insight_indicator": "\u2014"}, "4": {"last_funding_at": "\u2014"}, "5": {"last_funding_type": "\u2014"}, "6": {"contact_job_departments": "\u2014"}, "7": {"num_contacts": "\u2014"}, "8": {"num_employees_enum": "51-100"}, "9": {"founded_on": "2020"}, "10": {"categories": "Property Development, Real Estate, Residential"}, "11": {"location_identifiers": "Tulum, Quintana Roo, Mexico"}, "12": {"short_description": "Mistiq Tulum is a real estate development company for residential sector."}, "13": {"rank_org_company": "1,025,310"}, "14": {"location_group_identifiers": "Latin America"}, "15": {"linkedin": "https://www.linkedin.com/company/mistiq-tulum/"}, "16": {"contact_email": "sales@mistiqtulum.com"}, "17": {"phone_number": "+52 984 108 2556"}, "18": {"description": "\u2014"}, "19": {"founder_identifiers": "\u2014"}, "20": {"num_founders": "\u2014"}, "21": {"add_column": ""}, "length": 22, "prevObject": {"0": {"__ngContext__": 3854663}, "1": {"__ngContext__": 3855249}, "2": {"__ngContext__": 3855277}, "3": {"__ngContext__": 3855287}, "4": {"__ngContext__": 3855297}, "5": {"__ngContext__": 3855307}, "6": {"__ngContext__": 3855317}, "7": {"__ngContext__": 3855328}, "8": {"__ngContext__": 3855338}, "9": {"__ngContext__": 3855346}, "10": {"__ngContext__": 3855356}, "11": {"__ngContext__": 3855377}, "12": {"__ngContext__": 3855398}, "13": {"__ngContext__": 3855408}, "14": {"__ngContext__": 3855416}, "15": {"__ngContext__": 3855431}, "16": {"__ngContext__": 3855446}, "17": {"__ngContext__": 3855458}, "18": {"__ngContext__": 3855470}, "19": {"__ngContext__": 3855480}, "20": {"__ngContext__": 3855493}, "21": {"__ngContext__": 3854663}, "length": 22, "prevObject": {"0": {"__ngContext__": 3854663, "__zone_symbol__clickfalse": [{"type": "eventTask", "state": "scheduled", "source": "HTMLElement.addEventListener:click", "zone": "angular", "runCount": 0}], "__zone_symbol__mouseoverfalse": [{"type": "eventTask", "state": "scheduled", "source": "HTMLElement.addEventListener:mouseover", "zone": "angular", "runCount": 0}], "__zone_symbol__mouseoutfalse": [{"type": "eventTask", "state": "scheduled", "source": "HTMLElement.addEventListener:mouseout", "zone": "angular", "runCount": 0}]}, "length": 1}}}, {"0": {"select": ""}, "1": {"identifier": "Tan Tan"}, "2": {"last_key_employee_change_date": "\u2014"}, "3": {"growth_insight_indicator": "\u2014"}, "4": {"last_funding_at": "\u2014"}, "5": {"last_funding_type": "\u2014"}, "6": {"contact_job_departments": "\u2014"}, "7": {"num_contacts": "\u2014"}, "8": {"num_employees_enum": "1-10"}, "9": {"founded_on": "2020"}, "10": {"categories": "Artificial Intelligence (AI), Blockchain, FinTech, Payments"}, "11": {"location_identifiers": "Miguel Hidalgo, Distrito Federal, Mexico"}, "12": {"short_description": "Tan Tan is a fintech firm that offers a digital wallet with a high level of security based on AI and blockchain."}, "13": {"rank_org_company": "1,034,942"}, "14": {"location_group_identifiers": "Latin America"}, "15": {"linkedin": "https://www.linkedin.com/company/tantansolutions/about/"}, "16": {"contact_email": "hi@tantan.solutions"}, "17": {"phone_number": "+52 55 8363 7500"}, "18": {"description": "Tan Tan is a fintech firm that offers a digital wallet with a high level of security based on AI and blockchain."}, "19": {"founder_identifiers": "\u2014"}, "20": {"num_founders": "\u2014"}, "21": {"add_column": ""}, "length": 22, "prevObject": {"0": {"__ngContext__": 3854668}, "1": {"__ngContext__": 3855523}, "2": {"__ngContext__": 3855551}, "3": {"__ngContext__": 3855561}, "4": {"__ngContext__": 3855571}, "5": {"__ngContext__": 3855581}, "6": {"__ngContext__": 3855591}, "7": {"__ngContext__": 3855602}, "8": {"__ngContext__": 3855612}, "9": {"__ngContext__": 3855620}, "10": {"__ngContext__": 3855630}, "11": {"__ngContext__": 3855654}, "12": {"__ngContext__": 3855675}, "13": {"__ngContext__": 3855685}, "14": {"__ngContext__": 3855693}, "15": {"__ngContext__": 3855708}, "16": {"__ngContext__": 3855723}, "17": {"__ngContext__": 3855735}, "18": {"__ngContext__": 3855747}, "19": {"__ngContext__": 3855757}, "20": {"__ngContext__": 3855770}, "21": {"__ngContext__": 3854668}, "length": 22, "prevObject": {"0": {"__ngContext__": 3854668, "__zone_symbol__clickfalse": [{"type": "eventTask", "state": "scheduled", "source": "HTMLElement.addEventListener:click", "zone": "angular", "runCount": 0}], "__zone_symbol__mouseoverfalse": [{"type": "eventTask", "state": "scheduled", "source": "HTMLElement.addEventListener:mouseover", "zone": "angular", "runCount": 0}], "__zone_symbol__mouseoutfalse": [{"type": "eventTask", "state": "scheduled", "source": "HTMLElement.addEventListener:mouseout", "zone": "angular", "runCount": 0}]}, "length": 1}}}, {"0": {"select": ""}, "1": {"identifier": "Dan Estrategia"}, "2": {"last_key_employee_change_date": "\u2014"}, "3": {"growth_insight_indicator": "\u2014"}, "4": {"last_funding_at": "\u2014"}, "5": {"last_funding_type": "\u2014"}, "6": {"contact_job_departments": "\u2014"}, "7": {"num_contacts": "\u2014"}, "8": {"num_employees_enum": "1-10"}, "9": {"founded_on": "2020"}, "10": {"categories": "Advertising, Creative Agency, Legal, Marketing"}, "11": {"location_identifiers": "Mexico City, Distrito Federal, Mexico"}, "12": {"short_description": "Dan Estrategia is a creative agency that specializes in marketing, advertising, training, digitization, and legal services."}, "13": {"rank_org_company": "1,039,708"}, "14": {"location_group_identifiers": "Latin America"}, "15": {"linkedin": "https://www.linkedin.com/company/dan-estrategia"}, "16": {"contact_email": "contacto@danestrategia.com"}, "17": {"phone_number": "+52 55 3247 6400"}, "18": {"description": "\u2014"}, "19": {"founder_identifiers": "\u2014"}, "20": {"num_founders": "\u2014"}, "21": {"add_column": ""}, "length": 22, "prevObject": {"0": {"__ngContext__": 3854673}, "1": {"__ngContext__": 3855800}, "2": {"__ngContext__": 3855828}, "3": {"__ngContext__": 3855838}, "4": {"__ngContext__": 3855848}, "5": {"__ngContext__": 3855858}, "6": {"__ngContext__": 3855868}, "7": {"__ngContext__": 3855879}, "8": {"__ngContext__": 3855889}, "9": {"__ngContext__": 3855897}, "10": {"__ngContext__": 3855907}, "11": {"__ngContext__": 3855931}, "12": {"__ngContext__": 3855952}, "13": {"__ngContext__": 3855962}, "14": {"__ngContext__": 3855970}, "15": {"__ngContext__": 3855985}, "16": {"__ngContext__": 3856000}, "17": {"__ngContext__": 3856012}, "18": {"__ngContext__": 3856024}, "19": {"__ngContext__": 3856034}, "20": {"__ngContext__": 3856047}, "21": {"__ngContext__": 3854673}, "length": 22, "prevObject": {"0": {"__ngContext__": 3854673, "__zone_symbol__clickfalse": [{"type": "eventTask", "state": "scheduled", "source": "HTMLElement.addEventListener:click", "zone": "angular", "runCount": 0}], "__zone_symbol__mouseoverfalse": [{"type": "eventTask", "state": "scheduled", "source": "HTMLElement.addEventListener:mouseover", "zone": "angular", "runCount": 0}], "__zone_symbol__mouseoutfalse": [{"type": "eventTask", "state": "scheduled", "source": "HTMLElement.addEventListener:mouseout", "zone": "angular", "runCount": 0}]}, "length": 1}}}, {"0": {"select": ""}, "1": {"identifier": "SMI Canafe"}, "2": {"last_key_employee_change_date": "\u2014"}, "3": {"growth_insight_indicator": "\u2014"}, "4": {"last_funding_at": "\u2014"}, "5": {"last_funding_type": "\u2014"}, "6": {"contact_job_departments": "\u2014"}, "7": {"num_contacts": "\u2014"}, "8": {"num_employees_enum": "11-50"}, "9": {"founded_on": "2020"}, "10": {"categories": "Field Support, Industrial, Mechanical Engineering, Test and Measurement"}, "11": {"location_identifiers": "Fort\u00edn De Las Flores, Veracruz-Llave, Mexico"}, "12": {"short_description": "SMI Canafe installs, maintains, verifies, and commissions air conditioning and industrial measurement systems."}, "13": {"rank_org_company": "1,045,482"}, "14": {"location_group_identifiers": "Latin America"}, "15": {"linkedin": "https://www.linkedin.com/company/smi-canafe/"}, "16": {"contact_email": "sales@smicanafe.com"}, "17": {"phone_number": "+52 33 2386 3752"}, "18": {"description": "\u2014"}, "19": {"founder_identifiers": "\u2014"}, "20": {"num_founders": "\u2014"}, "21": {"add_column": ""}, "length": 22, "prevObject": {"0": {"__ngContext__": 3856057}, "1": {"__ngContext__": 3856102}, "2": {"__ngContext__": 3856130}, "3": {"__ngContext__": 3856140}, "4": {"__ngContext__": 3856150}, "5": {"__ngContext__": 3856160}, "6": {"__ngContext__": 3856170}, "7": {"__ngContext__": 3856181}, "8": {"__ngContext__": 3856191}, "9": {"__ngContext__": 3856199}, "10": {"__ngContext__": 3856209}, "11": {"__ngContext__": 3856233}, "12": {"__ngContext__": 3856254}, "13": {"__ngContext__": 3856264}, "14": {"__ngContext__": 3856272}, "15": {"__ngContext__": 3856287}, "16": {"__ngContext__": 3856302}, "17": {"__ngContext__": 3856314}, "18": {"__ngContext__": 3856326}, "19": {"__ngContext__": 3856336}, "20": {"__ngContext__": 3856349}, "21": {"__ngContext__": 3856057}, "length": 22, "prevObject": {"0": {"__ngContext__": 3856057, "__zone_symbol__clickfalse": [{"type": "eventTask", "state": "scheduled", "source": "HTMLElement.addEventListener:click", "zone": "angular", "runCount": 0}], "__zone_symbol__mouseoverfalse": [{"type": "eventTask", "state": "scheduled", "source": "HTMLElement.addEventListener:mouseover", "zone": "angular", "runCount": 0}], "__zone_symbol__mouseoutfalse": [{"type": "eventTask", "state": "scheduled", "source": "HTMLElement.addEventListener:mouseout", "zone": "angular", "runCount": 0}]}, "length": 1}}}, {"0": {"select": ""}, "1": {"identifier": "HIT Education"}, "2": {"last_key_employee_change_date": "\u2014"}, "3": {"growth_insight_indicator": "\u2014"}, "4": {"last_funding_at": "\u2014"}, "5": {"last_funding_type": "\u2014"}, "6": {"contact_job_departments": "\u2014"}, "7": {"num_contacts": "\u2014"}, "8": {"num_employees_enum": "11-50"}, "9": {"founded_on": "2020"}, "10": {"categories": "Education, Personal Development, Training"}, "11": {"location_identifiers": "Zapopan, Jalisco, Mexico"}, "12": {"short_description": "HIT Education is an educational firm that specializes in providing professional and personal training services."}, "13": {"rank_org_company": "1,046,266"}, "14": {"location_group_identifiers": "Latin America"}, "15": {"linkedin": "https://www.linkedin.com/company/hiteducation/"}, "16": {"contact_email": "direccion@hit-education.com"}, "17": {"phone_number": "\u2014"}, "18": {"description": "\u2014"}, "19": {"founder_identifiers": "\u2014"}, "20": {"num_founders": "\u2014"}, "21": {"add_column": ""}, "length": 22, "prevObject": {"0": {"__ngContext__": 3856062}, "1": {"__ngContext__": 3856379}, "2": {"__ngContext__": 3856407}, "3": {"__ngContext__": 3856417}, "4": {"__ngContext__": 3856427}, "5": {"__ngContext__": 3856437}, "6": {"__ngContext__": 3856447}, "7": {"__ngContext__": 3856458}, "8": {"__ngContext__": 3856468}, "9": {"__ngContext__": 3856476}, "10": {"__ngContext__": 3856486}, "11": {"__ngContext__": 3856507}, "12": {"__ngContext__": 3856528}, "13": {"__ngContext__": 3856538}, "14": {"__ngContext__": 3856546}, "15": {"__ngContext__": 3856561}, "16": {"__ngContext__": 3856576}, "17": {"__ngContext__": 3856588}, "18": {"__ngContext__": 3856599}, "19": {"__ngContext__": 3856609}, "20": {"__ngContext__": 3856622}, "21": {"__ngContext__": 3856062}, "length": 22, "prevObject": {"0": {"__ngContext__": 3856062, "__zone_symbol__clickfalse": [{"type": "eventTask", "state": "scheduled", "source": "HTMLElement.addEventListener:click", "zone": "angular", "runCount": 0}], "__zone_symbol__mouseoverfalse": [{"type": "eventTask", "state": "scheduled", "source": "HTMLElement.addEventListener:mouseover", "zone": "angular", "runCount": 0}], "__zone_symbol__mouseoutfalse": [{"type": "eventTask", "state": "scheduled", "source": "HTMLElement.addEventListener:mouseout", "zone": "angular", "runCount": 0}]}, "length": 1}}}, {"0": {"select": ""}, "1": {"identifier": "Velara Fintech"}, "2": {"last_key_employee_change_date": "\u2014"}, "3": {"growth_insight_indicator": "\u2014"}, "4": {"last_funding_at": "\u2014"}, "5": {"last_funding_type": "\u2014"}, "6": {"contact_job_departments": "\u2014"}, "7": {"num_contacts": "\u2014"}, "8": {"num_employees_enum": "1-10"}, "9": {"founded_on": "2020"}, "10": {"categories": "Commercial, Consulting, Financial Services"}, "11": {"location_identifiers": "Bogot\u00e1, Distrito Especial, Colombia"}, "12": {"short_description": "Velara Fintech provides financial services to both individuals and businesses."}, "13": {"rank_org_company": "1,052,739"}, "14": {"location_group_identifiers": "Latin America"}, "15": {"linkedin": "https://www.linkedin.com/company/velarafintech"}, "16": {"contact_email": "admin@velara.co"}, "17": {"phone_number": "+57 312 5812384"}, "18": {"description": "Velara Fintech provides commercial finance, and personal finance services. They also offer financial diagnosis, investments and start investing, and how to manage resources, debts, and working capital services."}, "19": {"founder_identifiers": "Jessica Olivan, Pamela Hollmann"}, "20": {"num_founders": "2"}, "21": {"add_column": ""}, "length": 22, "prevObject": {"0": {"__ngContext__": 3856067}, "1": {"__ngContext__": 3856652}, "2": {"__ngContext__": 3856680}, "3": {"__ngContext__": 3856690}, "4": {"__ngContext__": 3856700}, "5": {"__ngContext__": 3856710}, "6": {"__ngContext__": 3856720}, "7": {"__ngContext__": 3856731}, "8": {"__ngContext__": 3856741}, "9": {"__ngContext__": 3856749}, "10": {"__ngContext__": 3856759}, "11": {"__ngContext__": 3856780}, "12": {"__ngContext__": 3856801}, "13": {"__ngContext__": 3856811}, "14": {"__ngContext__": 3856819}, "15": {"__ngContext__": 3856834}, "16": {"__ngContext__": 3856849}, "17": {"__ngContext__": 3856861}, "18": {"__ngContext__": 3856873}, "19": {"__ngContext__": 3856883}, "20": {"__ngContext__": 3856901}, "21": {"__ngContext__": 3856067}, "length": 22, "prevObject": {"0": {"__ngContext__": 3856067, "__zone_symbol__clickfalse": [{"type": "eventTask", "state": "scheduled", "source": "HTMLElement.addEventListener:click", "zone": "angular", "runCount": 0}], "__zone_symbol__mouseoverfalse": [{"type": "eventTask", "state": "scheduled", "source": "HTMLElement.addEventListener:mouseover", "zone": "angular", "runCount": 0}], "__zone_symbol__mouseoutfalse": [{"type": "eventTask", "state": "scheduled", "source": "HTMLElement.addEventListener:mouseout", "zone": "angular", "runCount": 0}]}, "length": 1}}}, {"0": {"select": ""}, "1": {"identifier": "inXel"}, "2": {"last_key_employee_change_date": "\u2014"}, "3": {"growth_insight_indicator": "\u2014"}, "4": {"last_funding_at": "\u2014"}, "5": {"last_funding_type": "\u2014"}, "6": {"contact_job_departments": "\u2014"}, "7": {"num_contacts": "\u2014"}, "8": {"num_employees_enum": "11-50"}, "9": {"founded_on": "2020"}, "10": {"categories": "Internet, Mobile Payments, Telecommunications, Wireless"}, "11": {"location_identifiers": "Benito Ju\u00e1rez, Puebla, Mexico"}, "12": {"short_description": "inXel is a telecommunications services company that offers mobile telephony and internet services."}, "13": {"rank_org_company": "1,053,241"}, "14": {"location_group_identifiers": "Latin America"}, "15": {"linkedin": "https://www.linkedin.com/company/inxel-mx/"}, "16": {"contact_email": "sistencia@inxel.mx"}, "17": {"phone_number": "+52 55 8840 9522"}, "18": {"description": "\u2014"}, "19": {"founder_identifiers": "\u2014"}, "20": {"num_founders": "\u2014"}, "21": {"add_column": ""}, "length": 22, "prevObject": {"0": {"__ngContext__": 3856072}, "1": {"__ngContext__": 3856929}, "2": {"__ngContext__": 3856957}, "3": {"__ngContext__": 3856967}, "4": {"__ngContext__": 3856977}, "5": {"__ngContext__": 3856987}, "6": {"__ngContext__": 3856997}, "7": {"__ngContext__": 3857008}, "8": {"__ngContext__": 3857018}, "9": {"__ngContext__": 3857026}, "10": {"__ngContext__": 3857036}, "11": {"__ngContext__": 3857060}, "12": {"__ngContext__": 3857081}, "13": {"__ngContext__": 3857091}, "14": {"__ngContext__": 3857099}, "15": {"__ngContext__": 3857114}, "16": {"__ngContext__": 3857129}, "17": {"__ngContext__": 3857141}, "18": {"__ngContext__": 3857153}, "19": {"__ngContext__": 3857163}, "20": {"__ngContext__": 3857176}, "21": {"__ngContext__": 3856072}, "length": 22, "prevObject": {"0": {"__ngContext__": 3856072, "__zone_symbol__clickfalse": [{"type": "eventTask", "state": "scheduled", "source": "HTMLElement.addEventListener:click", "zone": "angular", "runCount": 0}], "__zone_symbol__mouseoverfalse": [{"type": "eventTask", "state": "scheduled", "source": "HTMLElement.addEventListener:mouseover", "zone": "angular", "runCount": 0}], "__zone_symbol__mouseoutfalse": [{"type": "eventTask", "state": "scheduled", "source": "HTMLElement.addEventListener:mouseout", "zone": "angular", "runCount": 0}]}, "length": 1}}}, {"0": {"select": ""}, "1": {"identifier": "Triskel Am\u00e9rica"}, "2": {"last_key_employee_change_date": "\u2014"}, "3": {"growth_insight_indicator": "\u2014"}, "4": {"last_funding_at": "\u2014"}, "5": {"last_funding_type": "\u2014"}, "6": {"contact_job_departments": "\u2014"}, "7": {"num_contacts": "\u2014"}, "8": {"num_employees_enum": "11-50"}, "9": {"founded_on": "2020"}, "10": {"categories": "Human Resources, Software, Training"}, "11": {"location_identifiers": "Monterrey, Nuevo Leon, Mexico"}, "12": {"short_description": "Triskel Am\u00e9rica is a human development company that specializes in the culture of applied learning, workshops, software, and courses."}, "13": {"rank_org_company": "1,056,458"}, "14": {"location_group_identifiers": "Latin America"}, "15": {"linkedin": "https://www.linkedin.com/company/triskelamericamty"}, "16": {"contact_email": "contact@triskelamerica.com"}, "17": {"phone_number": "+52 81 2108 7744"}, "18": {"description": "\u2014"}, "19": {"founder_identifiers": "\u2014"}, "20": {"num_founders": "\u2014"}, "21": {"add_column": ""}, "length": 22, "prevObject": {"0": {"__ngContext__": 3856077}, "1": {"__ngContext__": 3857206}, "2": {"__ngContext__": 3857234}, "3": {"__ngContext__": 3857244}, "4": {"__ngContext__": 3857254}, "5": {"__ngContext__": 3857264}, "6": {"__ngContext__": 3857274}, "7": {"__ngContext__": 3857285}, "8": {"__ngContext__": 3857295}, "9": {"__ngContext__": 3857303}, "10": {"__ngContext__": 3857313}, "11": {"__ngContext__": 3857334}, "12": {"__ngContext__": 3857355}, "13": {"__ngContext__": 3857365}, "14": {"__ngContext__": 3857373}, "15": {"__ngContext__": 3857388}, "16": {"__ngContext__": 3857403}, "17": {"__ngContext__": 3857415}, "18": {"__ngContext__": 3857427}, "19": {"__ngContext__": 3857437}, "20": {"__ngContext__": 3857450}, "21": {"__ngContext__": 3856077}, "length": 22, "prevObject": {"0": {"__ngContext__": 3856077, "__zone_symbol__clickfalse": [{"type": "eventTask", "state": "scheduled", "source": "HTMLElement.addEventListener:click", "zone": "angular", "runCount": 0}], "__zone_symbol__mouseoverfalse": [{"type": "eventTask", "state": "scheduled", "source": "HTMLElement.addEventListener:mouseover", "zone": "angular", "runCount": 0}], "__zone_symbol__mouseoutfalse": [{"type": "eventTask", "state": "scheduled", "source": "HTMLElement.addEventListener:mouseout", "zone": "angular", "runCount": 0}]}, "length": 1}}}, {"0": {"select": ""}, "1": {"identifier": "Due-Legal"}, "2": {"last_key_employee_change_date": "\u2014"}, "3": {"growth_insight_indicator": "\u2014"}, "4": {"last_funding_at": "\u2014"}, "5": {"last_funding_type": "\u2014"}, "6": {"contact_job_departments": "\u2014"}, "7": {"num_contacts": "\u2014"}, "8": {"num_employees_enum": "1-10"}, "9": {"founded_on": "2020"}, "10": {"categories": "Advice, Legal, Professional Services"}, "11": {"location_identifiers": "Bogot\u00e1, Distrito Especial, Colombia"}, "12": {"short_description": "Due-Legal is a law firm that offers legal services in the area of corporate, commercial, startup, intellectual property, and copyright."}, "13": {"rank_org_company": "1,058,574"}, "14": {"location_group_identifiers": "Latin America"}, "15": {"linkedin": "https://www.linkedin.com/company/due-legal/"}, "16": {"contact_email": "contact@due-legal.com"}, "17": {"phone_number": "+57-316-380-0025"}, "18": {"description": "\u2014"}, "19": {"founder_identifiers": "\u2014"}, "20": {"num_founders": "\u2014"}, "21": {"add_column": ""}, "length": 22, "prevObject": {"0": {"__ngContext__": 3857460}, "1": {"__ngContext__": 3857505}, "2": {"__ngContext__": 3857533}, "3": {"__ngContext__": 3857543}, "4": {"__ngContext__": 3857553}, "5": {"__ngContext__": 3857563}, "6": {"__ngContext__": 3857573}, "7": {"__ngContext__": 3857584}, "8": {"__ngContext__": 3857594}, "9": {"__ngContext__": 3857602}, "10": {"__ngContext__": 3857612}, "11": {"__ngContext__": 3857633}, "12": {"__ngContext__": 3857654}, "13": {"__ngContext__": 3857664}, "14": {"__ngContext__": 3857672}, "15": {"__ngContext__": 3857687}, "16": {"__ngContext__": 3857702}, "17": {"__ngContext__": 3857714}, "18": {"__ngContext__": 3857726}, "19": {"__ngContext__": 3857736}, "20": {"__ngContext__": 3857749}, "21": {"__ngContext__": 3857460}, "length": 22, "prevObject": {"0": {"__ngContext__": 3857460, "__zone_symbol__clickfalse": [{"type": "eventTask", "state": "scheduled", "source": "HTMLElement.addEventListener:click", "zone": "angular", "runCount": 0}], "__zone_symbol__mouseoverfalse": [{"type": "eventTask", "state": "scheduled", "source": "HTMLElement.addEventListener:mouseover", "zone": "angular", "runCount": 0}], "__zone_symbol__mouseoutfalse": [{"type": "eventTask", "state": "scheduled", "source": "HTMLElement.addEventListener:mouseout", "zone": "angular", "runCount": 0}]}, "length": 1}}}, {"0": {"select": ""}, "1": {"identifier": "Movon Logistics"}, "2": {"last_key_employee_change_date": "\u2014"}, "3": {"growth_insight_indicator": "\u2014"}, "4": {"last_funding_at": "\u2014"}, "5": {"last_funding_type": "\u2014"}, "6": {"contact_job_departments": "\u2014"}, "7": {"num_contacts": "\u2014"}, "8": {"num_employees_enum": "51-100"}, "9": {"founded_on": "2020"}, "10": {"categories": "Delivery, Logistics, Supply Chain Management"}, "11": {"location_identifiers": "Alvaro Obreg\u00f3n, Distrito Federal, Mexico"}, "12": {"short_description": "Movon Logistics is a logistics company that provides packaging, labeling, and delivery management services."}, "13": {"rank_org_company": "1,060,271"}, "14": {"location_group_identifiers": "Latin America"}, "15": {"linkedin": "https://www.linkedin.com/company/movonlogistcsolutions/"}, "16": {"contact_email": "contacto@movon.com.mx"}, "17": {"phone_number": "+52 55 8106 9511"}, "18": {"description": "\u2014"}, "19": {"founder_identifiers": "\u2014"}, "20": {"num_founders": "\u2014"}, "21": {"add_column": ""}, "length": 22, "prevObject": {"0": {"__ngContext__": 3857465}, "1": {"__ngContext__": 3857779}, "2": {"__ngContext__": 3857807}, "3": {"__ngContext__": 3857817}, "4": {"__ngContext__": 3857827}, "5": {"__ngContext__": 3857837}, "6": {"__ngContext__": 3857847}, "7": {"__ngContext__": 3857858}, "8": {"__ngContext__": 3857868}, "9": {"__ngContext__": 3857876}, "10": {"__ngContext__": 3857886}, "11": {"__ngContext__": 3857907}, "12": {"__ngContext__": 3857928}, "13": {"__ngContext__": 3857938}, "14": {"__ngContext__": 3857946}, "15": {"__ngContext__": 3857961}, "16": {"__ngContext__": 3857976}, "17": {"__ngContext__": 3857988}, "18": {"__ngContext__": 3858000}, "19": {"__ngContext__": 3858010}, "20": {"__ngContext__": 3858023}, "21": {"__ngContext__": 3857465}, "length": 22, "prevObject": {"0": {"__ngContext__": 3857465, "__zone_symbol__clickfalse": [{"type": "eventTask", "state": "scheduled", "source": "HTMLElement.addEventListener:click", "zone": "angular", "runCount": 0}], "__zone_symbol__mouseoverfalse": [{"type": "eventTask", "state": "scheduled", "source": "HTMLElement.addEventListener:mouseover", "zone": "angular", "runCount": 0}], "__zone_symbol__mouseoutfalse": [{"type": "eventTask", "state": "scheduled", "source": "HTMLElement.addEventListener:mouseout", "zone": "angular", "runCount": 0}]}, "length": 1}}}, {"0": {"select": ""}, "1": {"identifier": "Fudi Market"}, "2": {"last_key_employee_change_date": "\u2014"}, "3": {"growth_insight_indicator": "\u2014"}, "4": {"last_funding_at": "\u2014"}, "5": {"last_funding_type": "\u2014"}, "6": {"contact_job_departments": "\u2014"}, "7": {"num_contacts": "\u2014"}, "8": {"num_employees_enum": "1-10"}, "9": {"founded_on": "2020"}, "10": {"categories": "Cooking, E-Commerce, Food and Beverage"}, "11": {"location_identifiers": "Viamonte, Cordoba, Argentina"}, "12": {"short_description": "Fudi Market is an online store that sells gastronomic supplies with specialization in bakery, ice cream, cafeteria, and party favors."}, "13": {"rank_org_company": "1,064,107"}, "14": {"location_group_identifiers": "Latin America"}, "15": {"linkedin": "https://www.linkedin.com/company/fudi-market"}, "16": {"contact_email": "hello@fudimarket.com"}, "17": {"phone_number": "\u2014"}, "18": {"description": "\u2014"}, "19": {"founder_identifiers": "\u2014"}, "20": {"num_founders": "\u2014"}, "21": {"add_column": ""}, "length": 22, "prevObject": {"0": {"__ngContext__": 3857470}, "1": {"__ngContext__": 3858053}, "2": {"__ngContext__": 3858081}, "3": {"__ngContext__": 3858091}, "4": {"__ngContext__": 3858101}, "5": {"__ngContext__": 3858111}, "6": {"__ngContext__": 3858121}, "7": {"__ngContext__": 3858132}, "8": {"__ngContext__": 3858142}, "9": {"__ngContext__": 3858150}, "10": {"__ngContext__": 3858160}, "11": {"__ngContext__": 3858181}, "12": {"__ngContext__": 3858202}, "13": {"__ngContext__": 3858212}, "14": {"__ngContext__": 3858220}, "15": {"__ngContext__": 3858235}, "16": {"__ngContext__": 3858250}, "17": {"__ngContext__": 3858262}, "18": {"__ngContext__": 3858273}, "19": {"__ngContext__": 3858283}, "20": {"__ngContext__": 3858296}, "21": {"__ngContext__": 3857470}, "length": 22, "prevObject": {"0": {"__ngContext__": 3857470, "__zone_symbol__clickfalse": [{"type": "eventTask", "state": "scheduled", "source": "HTMLElement.addEventListener:click", "zone": "angular", "runCount": 0}], "__zone_symbol__mouseoverfalse": [{"type": "eventTask", "state": "scheduled", "source": "HTMLElement.addEventListener:mouseover", "zone": "angular", "runCount": 0}], "__zone_symbol__mouseoutfalse": [{"type": "eventTask", "state": "scheduled", "source": "HTMLElement.addEventListener:mouseout", "zone": "angular", "runCount": 0}]}, "length": 1}}}, {"0": {"select": ""}, "1": {"identifier": "Pei"}, "2": {"last_key_employee_change_date": "\u2014"}, "3": {"growth_insight_indicator": "\u2014"}, "4": {"last_funding_at": "\u2014"}, "5": {"last_funding_type": "\u2014"}, "6": {"contact_job_departments": "\u2014"}, "7": {"num_contacts": "\u2014"}, "8": {"num_employees_enum": "11-50"}, "9": {"founded_on": "2020"}, "10": {"categories": "FinTech, Information Technology, Mobile Apps, Mobile Payments, Software"}, "11": {"location_identifiers": "San Jos\u00e9, San Jose, Costa Rica"}, "12": {"short_description": "Pei is an app to send and request money from any account to anyone."}, "13": {"rank_org_company": "1,068,821"}, "14": {"location_group_identifiers": "Central America, Latin America"}, "15": {"linkedin": "https://www.linkedin.com/company/peilatam"}, "16": {"contact_email": "soporte@go-pei.com"}, "17": {"phone_number": "506 7036 3757"}, "18": {"description": "\u2014"}, "19": {"founder_identifiers": "\u2014"}, "20": {"num_founders": "\u2014"}, "21": {"add_column": ""}, "length": 22, "prevObject": {"0": {"__ngContext__": 3857475}, "1": {"__ngContext__": 3858326}, "2": {"__ngContext__": 3858354}, "3": {"__ngContext__": 3858364}, "4": {"__ngContext__": 3858374}, "5": {"__ngContext__": 3858384}, "6": {"__ngContext__": 3858394}, "7": {"__ngContext__": 3858405}, "8": {"__ngContext__": 3858415}, "9": {"__ngContext__": 3858423}, "10": {"__ngContext__": 3858433}, "11": {"__ngContext__": 3858460}, "12": {"__ngContext__": 3858481}, "13": {"__ngContext__": 3858491}, "14": {"__ngContext__": 3858499}, "15": {"__ngContext__": 3858517}, "16": {"__ngContext__": 3858532}, "17": {"__ngContext__": 3858544}, "18": {"__ngContext__": 3858556}, "19": {"__ngContext__": 3858566}, "20": {"__ngContext__": 3858579}, "21": {"__ngContext__": 3857475}, "length": 22, "prevObject": {"0": {"__ngContext__": 3857475, "__zone_symbol__clickfalse": [{"type": "eventTask", "state": "scheduled", "source": "HTMLElement.addEventListener:click", "zone": "angular", "runCount": 0}], "__zone_symbol__mouseoverfalse": [{"type": "eventTask", "state": "scheduled", "source": "HTMLElement.addEventListener:mouseover", "zone": "angular", "runCount": 0}], "__zone_symbol__mouseoutfalse": [{"type": "eventTask", "state": "scheduled", "source": "HTMLElement.addEventListener:mouseout", "zone": "angular", "runCount": 0}]}, "length": 1}}}, {"0": {"select": ""}, "1": {"identifier": "Dimapesa"}, "2": {"last_key_employee_change_date": "\u2014"}, "3": {"growth_insight_indicator": "\u2014"}, "4": {"last_funding_at": "\u2014"}, "5": {"last_funding_type": "\u2014"}, "6": {"contact_job_departments": "\u2014"}, "7": {"num_contacts": "\u2014"}, "8": {"num_employees_enum": "11-50"}, "9": {"founded_on": "2020"}, "10": {"categories": "Construction, Cosmetics, Industrial, Marketing"}, "11": {"location_identifiers": "M\u00e9rida, Yucatan, Mexico"}, "12": {"short_description": "Dimapesa specializes in equipment for the construction industry."}, "13": {"rank_org_company": "1,068,993"}, "14": {"location_group_identifiers": "Latin America"}, "15": {"linkedin": "https://www.linkedin.com/company/dimapesa/"}, "16": {"contact_email": "atencionaclientes@dimapesa.com"}, "17": {"phone_number": "+52  999 828 3078"}, "18": {"description": "\u2014"}, "19": {"founder_identifiers": "\u2014"}, "20": {"num_founders": "\u2014"}, "21": {"add_column": ""}, "length": 22, "prevObject": {"0": {"__ngContext__": 3857480}, "1": {"__ngContext__": 3858609}, "2": {"__ngContext__": 3858637}, "3": {"__ngContext__": 3858647}, "4": {"__ngContext__": 3858657}, "5": {"__ngContext__": 3858667}, "6": {"__ngContext__": 3858677}, "7": {"__ngContext__": 3858688}, "8": {"__ngContext__": 3858698}, "9": {"__ngContext__": 3858706}, "10": {"__ngContext__": 3858716}, "11": {"__ngContext__": 3858740}, "12": {"__ngContext__": 3858761}, "13": {"__ngContext__": 3858771}, "14": {"__ngContext__": 3858779}, "15": {"__ngContext__": 3858794}, "16": {"__ngContext__": 3858809}, "17": {"__ngContext__": 3858821}, "18": {"__ngContext__": 3858833}, "19": {"__ngContext__": 3858843}, "20": {"__ngContext__": 3858856}, "21": {"__ngContext__": 3857480}, "length": 22, "prevObject": {"0": {"__ngContext__": 3857480, "__zone_symbol__clickfalse": [{"type": "eventTask", "state": "scheduled", "source": "HTMLElement.addEventListener:click", "zone": "angular", "runCount": 0}], "__zone_symbol__mouseoverfalse": [{"type": "eventTask", "state": "scheduled", "source": "HTMLElement.addEventListener:mouseover", "zone": "angular", "runCount": 0}], "__zone_symbol__mouseoutfalse": [{"type": "eventTask", "state": "scheduled", "source": "HTMLElement.addEventListener:mouseout", "zone": "angular", "runCount": 0}]}, "length": 1}}}]